[{"model": "admin.logentry", "pk": 1, "fields": {"action_time": "2023-12-18T06:53:39.358Z", "user": 1, "content_type": 7, "object_id": "1", "object_repr": "เซ็นทรัล", "action_flag": 1, "change_message": "[{\"added\": {}}]"}}, {"model": "admin.logentry", "pk": 2, "fields": {"action_time": "2023-12-18T06:54:09.071Z", "user": 1, "content_type": 7, "object_id": "2", "object_repr": "วัดสิรินธรวราราม", "action_flag": 1, "change_message": "[{\"added\": {}}]"}}, {"model": "admin.logentry", "pk": 3, "fields": {"action_time": "2023-12-20T06:09:29.753Z", "user": 1, "content_type": 7, "object_id": "2", "object_repr": "location 1 name วัดสิรินธรวราราม rating 4.7 review 2500 type วัด image image/1835040_cOY1hB0.jpg", "action_flag": 3, "change_message": ""}}, {"model": "admin.logentry", "pk": 4, "fields": {"action_time": "2023-12-20T06:09:29.763Z", "user": 1, "content_type": 7, "object_id": "1", "object_repr": "location 1 name เซ็นทรัล rating 4.5 review 250 type ช็อปปิ้ง image image/979025f957f7452ea60e5d11f4bd4f3f_sEdRtIv.webp", "action_flag": 3, "change_message": ""}}, {"model": "admin.logentry", "pk": 5, "fields": {"action_time": "2024-02-02T06:45:05.471Z", "user": 1, "content_type": 7, "object_id": "82", "object_repr": "location https://www.google.co.th/maps/place/%E0%B8%AB%E0%B8%AD%E0%B9%84%E0%B8%95%E0%B8%A3%E0%B8%AB%E0%B8%A5%E0%B8%B1%E0%B8%81%E0%B8%84%E0%B8%B3%E0%B8%88%E0%B8%B1%E0%B8%99%E0%B8%97%E0%B8%A3%E0%B9%8C/d", "action_flag": 3, "change_message": ""}}, {"model": "admin.logentry", "pk": 6, "fields": {"action_time": "2024-02-02T06:45:05.481Z", "user": 1, "content_type": 7, "object_id": "81", "object_repr": "location https://www.google.co.th/maps/place/%E0%B8%97%E0%B8%B8%E0%B9%88%E0%B8%87%E0%B8%99%E0%B8%B2%E0%B8%A1%E0%B8%B7%E0%B8%AD%E0%B8%9B%E0%B8%A3%E0%B8%B2%E0%B8%9A%E2%80%8B+%E0%B8%88%E0%B8%AD%E0%B8%99%", "action_flag": 3, "change_message": ""}}, {"model": "admin.logentry", "pk": 7, "fields": {"action_time": "2024-02-02T06:45:05.488Z", "user": 1, "content_type": 7, "object_id": "80", "object_repr": "location https://www.google.co.th/maps/place/%E0%B8%9C%E0%B8%B2%E0%B9%82%E0%B8%AA%E0%B8%81/data=!4m7!3m6!1s0x3115bb782b9b4cb1:0x679a2e92a1da5a1f!8m2!3d15.4181331!4d105.5708919!16s%2Fg%2F11gmsd9pll!19s", "action_flag": 3, "change_message": ""}}, {"model": "admin.logentry", "pk": 8, "fields": {"action_time": "2024-02-02T06:45:05.495Z", "user": 1, "content_type": 7, "object_id": "79", "object_repr": "location https://www.google.co.th/maps/place/%E0%B8%81%E0%B8%B2%E0%B8%A3%E0%B8%97%E0%B9%88%E0%B8%AD%E0%B8%87%E0%B9%80%E0%B8%97%E0%B8%B5%E0%B9%88%E0%B8%A2%E0%B8%A7%E0%B9%81%E0%B8%AB%E0%B9%88%E0%B8%87%E", "action_flag": 3, "change_message": ""}}, {"model": "admin.logentry", "pk": 9, "fields": {"action_time": "2024-02-02T06:45:05.500Z", "user": 1, "content_type": 7, "object_id": "78", "object_repr": "location https://www.google.co.th/maps/place/MP+farm/data=!4m7!3m6!1s0x311671b8a21eb97d:0x96fa8d6497a97f8a!8m2!3d15.4649024!4d104.9175812!16s%2Fg%2F11m7xg9k6m!19sChIJfbkeorhxFjERin-pl2SN-pY?authuser=0", "action_flag": 3, "change_message": ""}}, {"model": "admin.logentry", "pk": 10, "fields": {"action_time": "2024-02-02T06:45:05.507Z", "user": 1, "content_type": 7, "object_id": "77", "object_repr": "location https://www.google.co.th/maps/place/%E0%B8%95%E0%B8%B1%E0%B8%99%E0%B9%84%E0%B8%97%E0%B8%A3%E0%B8%A2%E0%B8%B1%E0%B8%81%E0%B8%A9%E0%B9%8C+%E0%B8%AD%E0%B8%B8%E0%B8%9A%E0%B8%A5%E0%B8%A3%E0%B8%B2%", "action_flag": 3, "change_message": ""}}, {"model": "admin.logentry", "pk": 11, "fields": {"action_time": "2024-02-02T06:45:05.512Z", "user": 1, "content_type": 7, "object_id": "76", "object_repr": "location https://www.google.co.th/maps/place/%E0%B8%AA%E0%B8%A7%E0%B8%99%E0%B8%99%E0%B9%89%E0%B8%B3%E0%B8%AD%E0%B8%B8%E0%B8%9A%E0%B8%A5%E0%B8%97%E0%B8%AD%E0%B8%87%E0%B8%AB%E0%B8%A5%E0%B9%88%E0%B8%AD%E", "action_flag": 3, "change_message": ""}}, {"model": "admin.logentry", "pk": 12, "fields": {"action_time": "2024-02-02T06:45:05.518Z", "user": 1, "content_type": 7, "object_id": "75", "object_repr": "location https://www.google.co.th/maps/place/%E0%B8%AA%E0%B8%96%E0%B8%B2%E0%B8%99%E0%B8%B5%E0%B8%95%E0%B8%B3%E0%B8%A3%E0%B8%A7%E0%B8%88%E0%B8%97%E0%B9%88%E0%B8%AD%E0%B8%87%E0%B9%80%E0%B8%97%E0%B8%B5%E", "action_flag": 3, "change_message": ""}}, {"model": "admin.logentry", "pk": 13, "fields": {"action_time": "2024-02-02T06:45:05.525Z", "user": 1, "content_type": 7, "object_id": "74", "object_repr": "location https://www.google.co.th/maps/place/%E0%B8%A8%E0%B8%B2%E0%B8%A5%E0%B8%B2%E0%B8%A3%E0%B9%88%E0%B8%A7%E0%B8%A1%E0%B9%83%E0%B8%88%28SML%29+%E0%B8%8A%E0%B8%B8%E0%B8%A1%E0%B8%8A%E0%B8%99%E0%B8%A7%", "action_flag": 3, "change_message": ""}}, {"model": "admin.logentry", "pk": 14, "fields": {"action_time": "2024-02-02T06:45:05.530Z", "user": 1, "content_type": 7, "object_id": "73", "object_repr": "location https://www.google.co.th/maps/place/%E0%B8%AB%E0%B8%99%E0%B8%AD%E0%B8%87%E0%B8%8A%E0%B9%89%E0%B8%B2%E0%B8%87+%28%E0%B8%95.%E0%B8%AB%E0%B8%99%E0%B8%AD%E0%B8%87%E0%B8%82%E0%B8%AD%E0%B8%99%29/da", "action_flag": 3, "change_message": ""}}, {"model": "admin.logentry", "pk": 15, "fields": {"action_time": "2024-02-02T06:45:05.536Z", "user": 1, "content_type": 7, "object_id": "72", "object_repr": "location https://www.google.co.th/maps/place/lc95shop/data=!4m7!3m6!1s0x3116637e84e5a279:0x2b7b605079300b20!8m2!3d15.3199999!4d104.7637619!16s%2Fg%2F11thl9h0zw!19sChIJeaLlhH5jFjERIAsweVBgeys?authuser=", "action_flag": 3, "change_message": ""}}, {"model": "admin.logentry", "pk": 16, "fields": {"action_time": "2024-02-02T06:45:05.543Z", "user": 1, "content_type": 7, "object_id": "71", "object_repr": "location https://www.google.co.th/maps/place/%E0%B8%82%E0%B8%B1%E0%B8%A7%E0%B8%99%E0%B9%89%E0%B8%AD%E0%B8%A2%E0%B8%9A%E0%B9%89%E0%B8%B2%E0%B8%99%E0%B8%9A%E0%B8%B8%E0%B9%88%E0%B8%87%E0%B8%AB%E0%B8%A7%E", "action_flag": 3, "change_message": ""}}, {"model": "admin.logentry", "pk": 17, "fields": {"action_time": "2024-02-02T06:45:05.548Z", "user": 1, "content_type": 7, "object_id": "70", "object_repr": "location https://www.google.co.th/maps/place/%E0%B8%AA%E0%B8%B3%E0%B8%99%E0%B8%B1%E0%B8%81%E0%B8%87%E0%B8%B2%E0%B8%99%E0%B8%81%E0%B8%B2%E0%B8%A3%E0%B8%97%E0%B9%88%E0%B8%AD%E0%B8%87%E0%B9%80%E0%B8%97%E", "action_flag": 3, "change_message": ""}}, {"model": "admin.logentry", "pk": 18, "fields": {"action_time": "2024-02-02T06:45:05.555Z", "user": 1, "content_type": 7, "object_id": "69", "object_repr": "location https://www.google.co.th/maps/place/%E0%B8%AA%E0%B8%A7%E0%B8%99%E0%B9%84%E0%B8%A1%E0%B9%89%E0%B8%AA%E0%B8%B1%E0%B8%81+%E0%B8%A3%E0%B9%89%E0%B8%AD%E0%B8%A2+%E0%B8%A5%E0%B9%89%E0%B8%B2%E0%B8%99", "action_flag": 3, "change_message": ""}}, {"model": "admin.logentry", "pk": 19, "fields": {"action_time": "2024-02-02T06:45:05.561Z", "user": 1, "content_type": 7, "object_id": "68", "object_repr": "location https://www.google.co.th/maps/place/%E0%B8%99%E0%B9%89%E0%B8%B3%E0%B8%95%E0%B8%81%E0%B8%95%E0%B8%B2%E0%B8%94%E0%B9%82%E0%B8%95%E0%B8%99/data=!4m7!3m6!1s0x3115b4b938d0cca7:0xfcbdc87ba0054882!8", "action_flag": 3, "change_message": ""}}, {"model": "admin.logentry", "pk": 20, "fields": {"action_time": "2024-02-02T06:45:05.567Z", "user": 1, "content_type": 7, "object_id": "67", "object_repr": "location https://www.google.co.th/maps/place/%E0%B8%9A%E0%B9%89%E0%B8%B2%E0%B8%99%E0%B8%AA%E0%B8%A7%E0%B8%99%E0%B8%9B%E0%B8%A3%E0%B8%B0%E0%B8%AA%E0%B8%B2%E0%B8%A3%E0%B8%9E%E0%B8%A3/data=!4m7!3m6!1s0x3", "action_flag": 3, "change_message": ""}}, {"model": "admin.logentry", "pk": 21, "fields": {"action_time": "2024-02-02T06:45:05.573Z", "user": 1, "content_type": 7, "object_id": "66", "object_repr": "location https://www.google.co.th/maps/place/%E0%B8%9C%E0%B8%B2%E0%B8%A7%E0%B8%B1%E0%B8%94%E0%B9%83%E0%B8%88/data=!4m7!3m6!1s0x31144afa9fba3d6d:0xdb391c372499a504!8m2!3d15.2036173!4d105.4420724!16s%2F", "action_flag": 3, "change_message": ""}}, {"model": "admin.logentry", "pk": 22, "fields": {"action_time": "2024-02-02T06:45:05.579Z", "user": 1, "content_type": 7, "object_id": "65", "object_repr": "location https://www.google.co.th/maps/place/%E0%B8%98%E0%B8%A7%E0%B8%B1%E0%B8%8A%E0%B8%8A%E0%B8%B1%E0%B8%A2%E0%B9%81%E0%B8%AD%E0%B8%99%E0%B8%94%E0%B9%8C%E0%B9%81%E0%B8%9E%E0%B8%A5%E0%B8%99%E0%B8%95%E", "action_flag": 3, "change_message": ""}}, {"model": "admin.logentry", "pk": 23, "fields": {"action_time": "2024-02-02T06:45:05.584Z", "user": 1, "content_type": 7, "object_id": "64", "object_repr": "location https://www.google.co.th/maps/place/%E0%B8%97%E0%B8%B8%E0%B9%88%E0%B8%87%E0%B8%99%E0%B8%B2%E0%B8%9A%E0%B8%B1%E0%B8%A7%E0%B8%AB%E0%B9%88%E0%B8%AD%E0%B8%87%E0%B9%81%E0%B8%94%E0%B8%87/data=!4m7!", "action_flag": 3, "change_message": ""}}, {"model": "admin.logentry", "pk": 24, "fields": {"action_time": "2024-02-02T06:45:05.589Z", "user": 1, "content_type": 7, "object_id": "63", "object_repr": "location https://www.google.co.th/maps/place/%E0%B8%99%E0%B8%B2%E0%B8%AB%E0%B8%99%E0%B8%AD%E0%B8%87%E0%B9%81%E0%B8%84%E0%B8%99%E0%B9%81%E0%B8%94%E0%B8%99%E0%B8%AB%E0%B8%AD%E0%B8%A2%E0%B8%88%E0%B8%B5%E", "action_flag": 3, "change_message": ""}}, {"model": "admin.logentry", "pk": 25, "fields": {"action_time": "2024-02-02T06:45:05.594Z", "user": 1, "content_type": 7, "object_id": "62", "object_repr": "location https://www.google.co.th/maps/place/%E0%B8%AA%E0%B8%B0%E0%B8%9E%E0%B8%B2%E0%B8%99%E0%B9%84%E0%B8%A1%E0%B9%89%E0%B8%AD%E0%B8%A1%E0%B8%95%E0%B8%B0/data=!4m7!3m6!1s0x3116634a5cf5718d:0x23b187217", "action_flag": 3, "change_message": ""}}, {"model": "admin.logentry", "pk": 26, "fields": {"action_time": "2024-02-02T06:45:05.598Z", "user": 1, "content_type": 7, "object_id": "61", "object_repr": "location https://www.google.co.th/maps/place/%E0%B8%AD%E0%B8%9A%E0%B8%AA%E0%B8%A1%E0%B8%B8%E0%B8%99%E0%B9%84%E0%B8%9E%E0%B8%A3%E0%B8%A7%E0%B8%B1%E0%B8%94%E0%B8%AB%E0%B8%99%E0%B8%AD%E0%B8%87%E0%B8%9B%E", "action_flag": 3, "change_message": ""}}, {"model": "admin.logentry", "pk": 27, "fields": {"action_time": "2024-02-02T06:45:05.602Z", "user": 1, "content_type": 7, "object_id": "60", "object_repr": "location https://www.google.co.th/maps/place/%E0%B8%AE%E0%B8%B1%E0%B8%81%E0%B8%99%E0%B8%B0@%E0%B8%97%E0%B8%B8%E0%B9%88%E0%B8%87%E0%B8%99%E0%B8%B2%E0%B8%84%E0%B8%B3+%E0%B8%84%E0%B8%B2%E0%B9%80%E0%B8%9F", "action_flag": 3, "change_message": ""}}, {"model": "admin.logentry", "pk": 28, "fields": {"action_time": "2024-02-02T06:45:05.608Z", "user": 1, "content_type": 7, "object_id": "59", "object_repr": "location https://www.google.co.th/maps/place/%E0%B8%A7%E0%B8%B1%E0%B8%94%E0%B9%81%E0%B8%88%E0%B9%89%E0%B8%87/data=!4m7!3m6!1s0x311687cdacf2088f:0x94719e118d0f2dac!8m2!3d15.2366083!4d104.8601155!16s%2F", "action_flag": 3, "change_message": ""}}, {"model": "admin.logentry", "pk": 29, "fields": {"action_time": "2024-02-02T06:45:05.614Z", "user": 1, "content_type": 7, "object_id": "58", "object_repr": "location https://www.google.co.th/maps/place/%E0%B8%A8%E0%B8%B9%E0%B8%99%E0%B8%A2%E0%B9%8C%E0%B9%80%E0%B8%A3%E0%B8%B5%E0%B8%A2%E0%B8%99%E0%B8%A3%E0%B8%B9%E0%B9%89%E0%B8%A1%E0%B8%B5%E0%B8%8A%E0%B8%B5%E", "action_flag": 3, "change_message": ""}}, {"model": "admin.logentry", "pk": 30, "fields": {"action_time": "2024-02-02T06:45:05.619Z", "user": 1, "content_type": 7, "object_id": "57", "object_repr": "location https://www.google.co.th/maps/place/%E0%B8%AB%E0%B8%B2%E0%B8%94%E0%B8%AD%E0%B9%87%E0%B8%AD%E0%B8%94%E0%B8%AD%E0%B9%87%E0%B8%AD%E0%B8%94/data=!4m7!3m6!1s0x31168d3cd905fb0b:0xc105fc644973d406!8", "action_flag": 3, "change_message": ""}}, {"model": "admin.logentry", "pk": 31, "fields": {"action_time": "2024-02-02T06:45:05.624Z", "user": 1, "content_type": 7, "object_id": "56", "object_repr": "location https://www.google.co.th/maps/place/%E0%B8%AA%E0%B8%A7%E0%B8%99%E0%B8%AA%E0%B8%B1%E0%B8%95%E0%B8%A7%E0%B9%8C%E0%B8%AD%E0%B8%B8%E0%B8%9A%E0%B8%A5%E0%B8%A3%E0%B8%B2%E0%B8%8A%E0%B8%98%E0%B8%B2%E", "action_flag": 3, "change_message": ""}}, {"model": "admin.logentry", "pk": 32, "fields": {"action_time": "2024-02-02T06:45:05.629Z", "user": 1, "content_type": 7, "object_id": "55", "object_repr": "location https://www.google.co.th/maps/place/%E0%B8%AB%E0%B8%AD%E0%B9%84%E0%B8%95%E0%B8%A3%E0%B8%81%E0%B8%A5%E0%B8%B2%E0%B8%87%E0%B8%99%E0%B9%89%E0%B8%B3/data=!4m7!3m6!1s0x31168775d9d6c8c5:0x14ce55e53", "action_flag": 3, "change_message": ""}}, {"model": "admin.logentry", "pk": 33, "fields": {"action_time": "2024-02-02T06:45:05.633Z", "user": 1, "content_type": 7, "object_id": "54", "object_repr": "location https://www.google.co.th/maps/place/%E0%B8%9B%E0%B9%89%E0%B8%B2%E0%B8%A2%E0%B8%A2%E0%B8%B4%E0%B8%99%E0%B8%94%E0%B8%B5%E0%B8%95%E0%B9%89%E0%B8%AD%E0%B8%99%E0%B8%A3%E0%B8%B1%E0%B8%9A%E0%B8%AA%E", "action_flag": 3, "change_message": ""}}, {"model": "admin.logentry", "pk": 34, "fields": {"action_time": "2024-02-02T06:45:05.638Z", "user": 1, "content_type": 7, "object_id": "53", "object_repr": "location https://www.google.co.th/maps/place/%E0%B8%AB%E0%B8%B2%E0%B8%94%E0%B8%97%E0%B9%88%E0%B8%B2%E0%B9%82%E0%B8%AE%E0%B8%87+%E0%B8%88%E0%B8%B8%E0%B8%94%E0%B8%9A%E0%B8%A3%E0%B8%A3%E0%B8%88%E0%B8%9A%", "action_flag": 3, "change_message": ""}}, {"model": "admin.logentry", "pk": 35, "fields": {"action_time": "2024-02-02T06:45:05.644Z", "user": 1, "content_type": 7, "object_id": "52", "object_repr": "location https://www.google.co.th/maps/place/%E0%B8%97%E0%B9%88%E0%B8%AD%E0%B8%87%E0%B9%80%E0%B8%97%E0%B8%B5%E0%B9%88%E0%B8%A2%E0%B8%A7%E0%B9%80%E0%B8%8A%E0%B8%B4%E0%B8%87%E0%B9%80%E0%B8%81%E0%B8%A9%E", "action_flag": 3, "change_message": ""}}, {"model": "admin.logentry", "pk": 36, "fields": {"action_time": "2024-02-02T06:45:05.648Z", "user": 1, "content_type": 7, "object_id": "51", "object_repr": "location https://www.google.co.th/maps/place/%E0%B8%AD%E0%B8%B8%E0%B8%97%E0%B8%A2%E0%B8%B2%E0%B8%99%E0%B9%81%E0%B8%AB%E0%B9%88%E0%B8%87%E0%B8%8A%E0%B8%B2%E0%B8%95%E0%B8%B4%E0%B8%A0%E0%B8%B9%E0%B8%88%E", "action_flag": 3, "change_message": ""}}, {"model": "admin.logentry", "pk": 37, "fields": {"action_time": "2024-02-02T06:45:05.653Z", "user": 1, "content_type": 7, "object_id": "50", "object_repr": "location https://www.google.co.th/maps/place/%E0%B8%9A%E0%B9%89%E0%B8%B2%E0%B8%99%E0%B8%AA%E0%B8%A7%E0%B8%99%E0%B8%9B%E0%B8%B1%E0%B8%99%E0%B8%AA%E0%B8%B8%E0%B8%82%26%E0%B9%81%E0%B8%A5%E0%B8%8A%E0%B8%B", "action_flag": 3, "change_message": ""}}, {"model": "admin.logentry", "pk": 38, "fields": {"action_time": "2024-02-02T06:45:05.660Z", "user": 1, "content_type": 7, "object_id": "49", "object_repr": "location https://www.google.co.th/maps/place/%E0%B8%A7%E0%B8%B1%E0%B8%94%E0%B8%A8%E0%B8%A3%E0%B8%B5%E0%B8%AD%E0%B8%B8%E0%B8%9A%E0%B8%A5%E0%B8%A3%E0%B8%B1%E0%B8%95%E0%B8%99%E0%B8%B2%E0%B8%A3%E0%B8%B2%E", "action_flag": 3, "change_message": ""}}, {"model": "admin.logentry", "pk": 39, "fields": {"action_time": "2024-02-02T06:45:05.666Z", "user": 1, "content_type": 7, "object_id": "48", "object_repr": "location https://www.google.co.th/maps/place/%E0%B8%97%E0%B8%B8%E0%B9%88%E0%B8%87%E0%B8%94%E0%B8%AD%E0%B8%81%E0%B8%AA%E0%B8%A3%E0%B9%89%E0%B8%AD%E0%B8%A2%E0%B8%AA%E0%B8%B8%E0%B8%A7%E0%B8%A3%E0%B8%A3%E", "action_flag": 3, "change_message": ""}}, {"model": "admin.logentry", "pk": 40, "fields": {"action_time": "2024-02-02T06:45:05.681Z", "user": 1, "content_type": 7, "object_id": "47", "object_repr": "location https://www.google.co.th/maps/place/%E0%B8%AD%E0%B8%B8%E0%B8%97%E0%B8%A2%E0%B8%B2%E0%B8%99%E0%B9%81%E0%B8%AB%E0%B9%88%E0%B8%87%E0%B8%8A%E0%B8%B2%E0%B8%95%E0%B8%B4%E0%B8%9C%E0%B8%B2%E0%B9%81%E", "action_flag": 3, "change_message": ""}}, {"model": "admin.logentry", "pk": 41, "fields": {"action_time": "2024-02-02T06:45:05.687Z", "user": 1, "content_type": 7, "object_id": "46", "object_repr": "location https://www.google.co.th/maps/place/%E0%B8%AA%E0%B8%A7%E0%B8%99%E0%B9%80%E0%B8%AA%E0%B8%B7%E0%B8%AD%E0%B8%95%E0%B8%A3%E0%B8%B0%E0%B8%81%E0%B8%B2%E0%B8%A3/data=!4m7!3m6!1s0x311675bd88c8098f:0x", "action_flag": 3, "change_message": ""}}, {"model": "admin.logentry", "pk": 42, "fields": {"action_time": "2024-02-02T06:45:05.691Z", "user": 1, "content_type": 7, "object_id": "45", "object_repr": "location https://www.google.co.th/maps/place/Ubon+Street+Art+-+Happiness+%28%E0%B8%84%E0%B8%A7%E0%B8%B2%E0%B8%A1%E0%B8%AA%E0%B8%B8%E0%B8%82%29/data=!4m7!3m6!1s0x3116870414162aff:0xc1f9d63cf78b5a80!8m2", "action_flag": 3, "change_message": ""}}, {"model": "admin.logentry", "pk": 43, "fields": {"action_time": "2024-02-02T06:45:05.696Z", "user": 1, "content_type": 7, "object_id": "44", "object_repr": "location https://www.google.co.th/maps/place/%E0%B9%82%E0%B8%9A%E0%B8%A3%E0%B8%B2%E0%B8%93%E0%B8%AA%E0%B8%96%E0%B8%B2%E0%B8%99%E0%B9%82%E0%B8%99%E0%B8%99%E0%B9%81%E0%B8%81/data=!4m7!3m6!1s0x31169accd2", "action_flag": 3, "change_message": ""}}, {"model": "admin.logentry", "pk": 44, "fields": {"action_time": "2024-02-02T06:45:05.700Z", "user": 1, "content_type": 7, "object_id": "43", "object_repr": "location https://www.google.co.th/maps/place/%E0%B8%A7%E0%B8%B1%E0%B8%94%E0%B8%96%E0%B9%89%E0%B8%B3%E0%B9%80%E0%B8%AB%E0%B8%A7%E0%B8%AA%E0%B8%B4%E0%B8%99%E0%B8%98%E0%B8%B8%E0%B9%8C%E0%B8%8A%E0%B8%B1%E", "action_flag": 3, "change_message": ""}}, {"model": "admin.logentry", "pk": 45, "fields": {"action_time": "2024-02-02T06:45:05.705Z", "user": 1, "content_type": 7, "object_id": "42", "object_repr": "location https://www.google.co.th/maps/place/%E0%B8%A0%E0%B8%B9%E0%B8%AB%E0%B8%B4%E0%B8%99%E0%B8%94%E0%B9%88%E0%B8%B2%E0%B8%87/data=!4m7!3m6!1s0x31140ca9d71f05b3:0x91efc93e9bce7860!8m2!3d14.4714583!4d", "action_flag": 3, "change_message": ""}}, {"model": "admin.logentry", "pk": 46, "fields": {"action_time": "2024-02-02T06:45:05.710Z", "user": 1, "content_type": 7, "object_id": "41", "object_repr": "location https://www.google.co.th/maps/place/%E0%B9%81%E0%B8%81%E0%B9%88%E0%B8%87%E0%B8%A5%E0%B8%B3%E0%B8%94%E0%B8%A7%E0%B8%99/data=!4m7!3m6!1s0x3114317d31476a1f:0x23c71e0ba2c752bf!8m2!3d15.1578792!4d", "action_flag": 3, "change_message": ""}}, {"model": "admin.logentry", "pk": 47, "fields": {"action_time": "2024-02-02T06:45:05.715Z", "user": 1, "content_type": 7, "object_id": "40", "object_repr": "location https://www.google.co.th/maps/place/%E0%B8%99%E0%B9%89%E0%B8%B3%E0%B8%95%E0%B8%81%E0%B8%AB%E0%B9%89%E0%B8%A7%E0%B8%A2%E0%B8%97%E0%B8%A3%E0%B8%B2%E0%B8%A2%E0%B9%83%E0%B8%AB%E0%B8%8D%E0%B9%88/d", "action_flag": 3, "change_message": ""}}, {"model": "admin.logentry", "pk": 48, "fields": {"action_time": "2024-02-02T06:45:05.720Z", "user": 1, "content_type": 7, "object_id": "39", "object_repr": "location https://www.google.co.th/maps/place/%E0%B8%9C%E0%B8%B2%E0%B8%8A%E0%B8%B0%E0%B8%99%E0%B8%B0%E0%B9%84%E0%B8%94/data=!4m7!3m6!1s0x31159838a3d50d97:0x49d6d8df167d1ce5!8m2!3d15.6208234!4d105.61736", "action_flag": 3, "change_message": ""}}, {"model": "admin.logentry", "pk": 49, "fields": {"action_time": "2024-02-02T06:45:05.724Z", "user": 1, "content_type": 7, "object_id": "38", "object_repr": "location https://www.google.co.th/maps/place/%E0%B8%AD%E0%B8%B8%E0%B8%97%E0%B8%A2%E0%B8%B2%E0%B8%99%E0%B9%81%E0%B8%AB%E0%B9%88%E0%B8%87%E0%B8%8A%E0%B8%B2%E0%B8%95%E0%B8%B4%E0%B9%81%E0%B8%81%E0%B9%88%E", "action_flag": 3, "change_message": ""}}, {"model": "admin.logentry", "pk": 50, "fields": {"action_time": "2024-02-02T06:45:05.729Z", "user": 1, "content_type": 7, "object_id": "37", "object_repr": "location https://www.google.co.th/maps/place/%E0%B8%95%E0%B8%B2%E0%B8%A1%E0%B8%A3%E0%B8%AD%E0%B8%A2%E0%B8%A0%E0%B8%B2%E0%B8%9E%E0%B8%A2%E0%B8%99%E0%B8%95%E0%B9%8C+Alexander/data=!4m7!3m6!1s0x311681454", "action_flag": 3, "change_message": ""}}, {"model": "admin.logentry", "pk": 51, "fields": {"action_time": "2024-02-02T06:45:05.734Z", "user": 1, "content_type": 7, "object_id": "36", "object_repr": "location https://www.google.co.th/maps/place/%E0%B9%81%E0%B8%81%E0%B9%88%E0%B8%87%E0%B8%AA%E0%B8%B0%E0%B8%9E%E0%B8%B7%E0%B8%AD/data=!4m7!3m6!1s0x311432c9d9705d45:0xa2dc6bdcad0c3303!8m2!3d15.2461458!4d", "action_flag": 3, "change_message": ""}}, {"model": "admin.logentry", "pk": 52, "fields": {"action_time": "2024-02-02T06:45:05.739Z", "user": 1, "content_type": 7, "object_id": "35", "object_repr": "location https://www.google.co.th/maps/place/%E0%B8%9C%E0%B8%B2%E0%B8%8A%E0%B8%B1%E0%B8%99+%E0%B8%AD%E0%B8%B8%E0%B8%9A%E0%B8%A5%E0%B8%A3%E0%B8%B2%E0%B8%8A%E0%B8%98%E0%B8%B2%E0%B8%99%E0%B8%B5/data=!4m7", "action_flag": 3, "change_message": ""}}, {"model": "admin.logentry", "pk": 53, "fields": {"action_time": "2024-02-02T06:45:05.749Z", "user": 1, "content_type": 7, "object_id": "34", "object_repr": "location https://www.google.co.th/maps/place/Ubon+Street+Art+-+The+Ubonratchathani/data=!4m7!3m6!1s0x31168796f10baf6f:0xa064aff7ce305361!8m2!3d15.2271084!4d104.8576992!16s%2Fg%2F11jzw8jb_y!19sChIJb68L", "action_flag": 3, "change_message": ""}}, {"model": "admin.logentry", "pk": 54, "fields": {"action_time": "2024-02-02T06:45:05.755Z", "user": 1, "content_type": 7, "object_id": "33", "object_repr": "location https://www.google.co.th/maps/place/%E0%B8%A7%E0%B8%B1%E0%B8%94%E0%B8%AA%E0%B8%B4%E0%B8%A3%E0%B8%B4%E0%B8%99%E0%B8%98%E0%B8%A3%E0%B8%A7%E0%B8%A3%E0%B8%B2%E0%B8%A3%E0%B8%B2%E0%B8%A1%E0%B8%A0%E", "action_flag": 3, "change_message": ""}}, {"model": "admin.logentry", "pk": 55, "fields": {"action_time": "2024-02-02T06:45:05.761Z", "user": 1, "content_type": 7, "object_id": "32", "object_repr": "location https://www.google.co.th/maps/place/%E0%B8%99%E0%B9%89%E0%B8%B3%E0%B8%95%E0%B8%81%E0%B8%AB%E0%B9%89%E0%B8%A7%E0%B8%A2%E0%B8%AB%E0%B8%A5%E0%B8%A7%E0%B8%87+%E0%B8%A0%E0%B8%B9%E0%B8%88%E0%B8%AD%", "action_flag": 3, "change_message": ""}}, {"model": "admin.logentry", "pk": 56, "fields": {"action_time": "2024-02-02T06:45:05.765Z", "user": 1, "content_type": 7, "object_id": "31", "object_repr": "location https://www.google.co.th/maps/place/%E0%B8%99%E0%B9%89%E0%B8%B3%E0%B8%95%E0%B8%81%E0%B9%81%E0%B8%AA%E0%B8%87%E0%B8%88%E0%B8%B1%E0%B8%99%E0%B8%97%E0%B8%A3%E0%B9%8C+%28%E0%B8%99%E0%B9%89%E0%B8%", "action_flag": 3, "change_message": ""}}, {"model": "admin.logentry", "pk": 57, "fields": {"action_time": "2024-02-02T06:45:05.770Z", "user": 1, "content_type": 7, "object_id": "30", "object_repr": "location https://www.google.co.th/maps/place/%E0%B8%A8%E0%B8%B9%E0%B8%99%E0%B8%A2%E0%B9%8C%E0%B8%A8%E0%B8%B4%E0%B8%A5%E0%B8%9B%E0%B8%A7%E0%B8%B1%E0%B8%92%E0%B8%99%E0%B8%98%E0%B8%A3%E0%B8%A3%E0%B8%A1%E", "action_flag": 3, "change_message": ""}}, {"model": "admin.logentry", "pk": 58, "fields": {"action_time": "2024-02-02T06:45:05.776Z", "user": 1, "content_type": 7, "object_id": "29", "object_repr": "location https://www.google.co.th/maps/place/%E0%B8%AD%E0%B9%88%E0%B8%B2%E0%B8%87%E0%B9%80%E0%B8%81%E0%B9%87%E0%B8%9A%E0%B8%99%E0%B9%89%E0%B8%B3%E0%B8%AB%E0%B9%89%E0%B8%A7%E0%B8%A2%E0%B9%81%E0%B8%88%E", "action_flag": 3, "change_message": ""}}, {"model": "admin.logentry", "pk": 59, "fields": {"action_time": "2024-02-02T06:45:05.780Z", "user": 1, "content_type": 7, "object_id": "28", "object_repr": "location https://www.google.co.th/maps/place/%E0%B8%A7%E0%B8%B1%E0%B8%94%E0%B8%AB%E0%B8%99%E0%B8%AD%E0%B8%87%E0%B8%9B%E0%B9%88%E0%B8%B2%E0%B8%9E%E0%B8%87+%28%E0%B8%AB%E0%B8%A5%E0%B8%A7%E0%B8%87%E0%B8%", "action_flag": 3, "change_message": ""}}, {"model": "admin.logentry", "pk": 60, "fields": {"action_time": "2024-02-02T06:45:05.784Z", "user": 1, "content_type": 7, "object_id": "27", "object_repr": "location https://www.google.co.th/maps/place/%E0%B8%9A%E0%B9%88%E0%B8%AD+%E0%B8%81%E0%B8%B0%E0%B9%81%E0%B8%A1%E0%B8%94/data=!4m7!3m6!1s0x31168547cc7a99eb:0xf227a7e2175cef63!8m2!3d15.1088138!4d104.9163", "action_flag": 3, "change_message": ""}}, {"model": "admin.logentry", "pk": 61, "fields": {"action_time": "2024-02-02T06:45:05.790Z", "user": 1, "content_type": 7, "object_id": "26", "object_repr": "location https://www.google.co.th/maps/place/%E0%B8%99%E0%B9%89%E0%B8%B3%E0%B8%95%E0%B8%81%E0%B9%82%E0%B8%9A%E0%B8%81%E0%B8%A5%E0%B8%B6%E0%B8%81/data=!4m7!3m6!1s0x3115be52a1e5ab87:0x30f76b949df6c44e!8", "action_flag": 3, "change_message": ""}}, {"model": "admin.logentry", "pk": 62, "fields": {"action_time": "2024-02-02T06:45:05.795Z", "user": 1, "content_type": 7, "object_id": "25", "object_repr": "location https://www.google.co.th/maps/place/%E0%B8%AB%E0%B8%B2%E0%B8%94%E0%B8%AB%E0%B8%87%E0%B8%AA%E0%B9%8C/data=!4m7!3m6!1s0x31158d2eec745c4d:0x2fec22138d3a2209!8m2!3d15.792802!4d105.4110691!16s%2Fg", "action_flag": 3, "change_message": ""}}, {"model": "admin.logentry", "pk": 63, "fields": {"action_time": "2024-02-02T06:45:05.800Z", "user": 1, "content_type": 7, "object_id": "24", "object_repr": "location https://www.google.co.th/maps/place/%E0%B8%A7%E0%B8%B1%E0%B8%94%E0%B8%96%E0%B9%89%E0%B8%B3%E0%B8%84%E0%B8%B9%E0%B8%AB%E0%B8%B2%E0%B8%AA%E0%B8%A7%E0%B8%A3%E0%B8%A3%E0%B8%84%E0%B9%8C+%E0%B8%AD%", "action_flag": 3, "change_message": ""}}, {"model": "admin.logentry", "pk": 64, "fields": {"action_time": "2024-02-02T06:45:05.805Z", "user": 1, "content_type": 7, "object_id": "23", "object_repr": "location https://www.google.co.th/maps/place/%E0%B8%A0%E0%B8%B2%E0%B8%9E%E0%B9%80%E0%B8%82%E0%B8%B5%E0%B8%A2%E0%B8%99%E0%B8%AA%E0%B8%B5+%28%E0%B8%9C%E0%B8%B2%E0%B8%AB%E0%B8%A1%E0%B8%AD%E0%B8%99%E0%B8%", "action_flag": 3, "change_message": ""}}, {"model": "admin.logentry", "pk": 65, "fields": {"action_time": "2024-02-02T06:45:05.809Z", "user": 1, "content_type": 7, "object_id": "22", "object_repr": "location https://www.google.co.th/maps/place/Graffiti+wall/data=!4m7!3m6!1s0x311687290d089905:0x97f4a58fee5155a8!8m2!3d15.2259389!4d104.8674571!16s%2Fg%2F11fnpldtm6!19sChIJBZkIDSmHFjERqFVR7o-l9Jc?auth", "action_flag": 3, "change_message": ""}}, {"model": "admin.logentry", "pk": 66, "fields": {"action_time": "2024-02-02T06:45:05.815Z", "user": 1, "content_type": 7, "object_id": "21", "object_repr": "location https://www.google.co.th/maps/place/%E0%B8%94%E0%B8%AD%E0%B8%81%E0%B8%AD%E0%B9%89%E0%B8%AD%E0%B8%97%E0%B8%B8%E0%B9%88%E0%B8%87%E0%B8%99%E0%B8%B2%E0%B8%9B%E0%B9%88%E0%B8%B2%E0%B8%9A%E0%B8%B1%E", "action_flag": 3, "change_message": ""}}, {"model": "admin.logentry", "pk": 67, "fields": {"action_time": "2024-02-02T06:45:05.822Z", "user": 1, "content_type": 7, "object_id": "20", "object_repr": "location https://www.google.co.th/maps/place/%E0%B8%99%E0%B9%89%E0%B8%B3%E0%B8%95%E0%B8%81%E0%B8%97%E0%B8%B8%E0%B9%88%E0%B8%87%E0%B8%99%E0%B8%B2%E0%B9%80%E0%B8%A1%E0%B8%B7%E0%B8%AD%E0%B8%87/data=!4m7!", "action_flag": 3, "change_message": ""}}, {"model": "admin.logentry", "pk": 68, "fields": {"action_time": "2024-02-02T06:45:05.828Z", "user": 1, "content_type": 7, "object_id": "19", "object_repr": "location https://www.google.co.th/maps/place/%E0%B8%9B%E0%B9%88%E0%B8%B2%E0%B8%94%E0%B8%87%E0%B8%99%E0%B8%B2%E0%B8%97%E0%B8%B2%E0%B8%A1/data=!4m7!3m6!1s0x3115bd9d7fc1cddb:0x3d3948b9d64a5e8e!8m2!3d15.5", "action_flag": 3, "change_message": ""}}, {"model": "admin.logentry", "pk": 69, "fields": {"action_time": "2024-02-02T06:45:05.833Z", "user": 1, "content_type": 7, "object_id": "18", "object_repr": "location https://www.google.co.th/maps/place/%E0%B8%97%E0%B8%B8%E0%B9%88%E0%B8%87%E0%B8%94%E0%B8%AD%E0%B8%81%E0%B8%97%E0%B8%B2%E0%B8%99%E0%B8%95%E0%B8%B0%E0%B8%A7%E0%B8%B1%E0%B8%99+%E0%B8%9A%E0%B9%89%", "action_flag": 3, "change_message": ""}}, {"model": "admin.logentry", "pk": 70, "fields": {"action_time": "2024-02-02T06:45:05.839Z", "user": 1, "content_type": 7, "object_id": "17", "object_repr": "location https://www.google.co.th/maps/place/%E0%B8%AA%E0%B8%B2%E0%B8%A1%E0%B8%9E%E0%B8%B1%E0%B8%99%E0%B9%82%E0%B8%9A%E0%B8%81/data=!4m7!3m6!1s0x3115ed1aaaaaaaab:0xeefee5c8280563c2!8m2!3d15.7970209!4d", "action_flag": 3, "change_message": ""}}, {"model": "admin.logentry", "pk": 71, "fields": {"action_time": "2024-02-02T06:45:05.843Z", "user": 1, "content_type": 7, "object_id": "16", "object_repr": "location https://www.google.co.th/maps/place/%E0%B8%99%E0%B9%89%E0%B8%B3%E0%B8%95%E0%B8%81%E0%B8%AA%E0%B8%A3%E0%B9%89%E0%B8%AD%E0%B8%A2%E0%B8%AA%E0%B8%A7%E0%B8%A3%E0%B8%A3%E0%B8%84%E0%B9%8C/data=!4m7!", "action_flag": 3, "change_message": ""}}, {"model": "admin.logentry", "pk": 72, "fields": {"action_time": "2024-02-02T06:45:05.850Z", "user": 1, "content_type": 7, "object_id": "15", "object_repr": "location https://www.google.co.th/maps/place/%E0%B9%80%E0%B8%82%E0%B8%B7%E0%B9%88%E0%B8%AD%E0%B8%99%E0%B8%AA%E0%B8%B4%E0%B8%A3%E0%B8%B4%E0%B8%99%E0%B8%98%E0%B8%A3/data=!4m7!3m6!1s0x31144a92a6b593b5:0x", "action_flag": 3, "change_message": ""}}, {"model": "admin.logentry", "pk": 73, "fields": {"action_time": "2024-02-02T06:45:05.857Z", "user": 1, "content_type": 7, "object_id": "14", "object_repr": "location https://www.google.co.th/maps/place/%E0%B8%97%E0%B8%B8%E0%B9%88%E0%B8%87%E0%B8%94%E0%B8%AD%E0%B8%81%E0%B8%AB%E0%B8%8D%E0%B9%89%E0%B8%B2+%28%E0%B8%AB%E0%B8%99%E0%B8%AD%E0%B8%87%E0%B8%AB%E0%B8%", "action_flag": 3, "change_message": ""}}, {"model": "admin.logentry", "pk": 74, "fields": {"action_time": "2024-02-02T06:45:05.862Z", "user": 1, "content_type": 7, "object_id": "13", "object_repr": "location https://www.google.co.th/maps/place/%E0%B8%A7%E0%B8%B1%E0%B8%94%E0%B8%97%E0%B8%B8%E0%B9%88%E0%B8%87%E0%B8%A8%E0%B8%A3%E0%B8%B5%E0%B9%80%E0%B8%A1%E0%B8%B7%E0%B8%AD%E0%B8%87/data=!4m7!3m6!1s0x3", "action_flag": 3, "change_message": ""}}, {"model": "admin.logentry", "pk": 75, "fields": {"action_time": "2024-02-02T06:45:05.867Z", "user": 1, "content_type": 7, "object_id": "12", "object_repr": "location https://www.google.co.th/maps/place/%E0%B8%82%E0%B8%B1%E0%B8%A7%E0%B8%99%E0%B9%89%E0%B8%AD%E0%B8%A2%E0%B8%9A%E0%B9%89%E0%B8%B2%E0%B8%99%E0%B8%8A%E0%B8%B5%E0%B8%97%E0%B8%A7%E0%B8%99/data=!4m7!", "action_flag": 3, "change_message": ""}}, {"model": "admin.logentry", "pk": 76, "fields": {"action_time": "2024-02-02T06:45:05.873Z", "user": 1, "content_type": 7, "object_id": "11", "object_repr": "location https://www.google.co.th/maps/place/%E0%B8%9E%E0%B8%B1%E0%B8%97%E0%B8%A2%E0%B8%B2%E0%B8%99%E0%B9%89%E0%B8%AD%E0%B8%A2+%E0%B8%AD%E0%B8%B8%E0%B8%9A%E0%B8%A5%E0%B8%A3%E0%B8%B2%E0%B8%8A%E0%B8%98%", "action_flag": 3, "change_message": ""}}, {"model": "admin.logentry", "pk": 77, "fields": {"action_time": "2024-02-02T06:45:05.879Z", "user": 1, "content_type": 7, "object_id": "10", "object_repr": "location https://www.google.co.th/maps/place/%E0%B8%AB%E0%B8%B2%E0%B8%94%E0%B8%8A%E0%B8%A1%E0%B8%94%E0%B8%B2%E0%B8%A7,+%E0%B9%81%E0%B8%81%E0%B9%88%E0%B8%87%E0%B8%8A%E0%B8%A1%E0%B8%94%E0%B8%B2%E0%B8%A7", "action_flag": 3, "change_message": ""}}, {"model": "admin.logentry", "pk": 78, "fields": {"action_time": "2024-02-02T06:45:05.885Z", "user": 1, "content_type": 7, "object_id": "9", "object_repr": "location https://www.google.co.th/maps/place/%E0%B9%80%E0%B8%97%E0%B8%B5%E0%B9%88%E0%B8%A2%E0%B8%A7%E0%B8%88%E0%B8%B1%E0%B8%87%E0%B8%AB%E0%B8%A7%E0%B8%B1%E0%B8%94%E0%B8%AD%E0%B8%B8%E0%B8%9A%E0%B8%A5%E", "action_flag": 3, "change_message": ""}}, {"model": "admin.logentry", "pk": 79, "fields": {"action_time": "2024-02-02T06:45:05.891Z", "user": 1, "content_type": 7, "object_id": "8", "object_repr": "location https://www.google.co.th/maps/place/%E0%B8%AB%E0%B8%B2%E0%B8%94%E0%B8%84%E0%B8%B9%E0%B9%80%E0%B8%94%E0%B8%B7%E0%B9%88%E0%B8%AD/data=!4m7!3m6!1s0x311689215d6532b1:0xb2e2cf45d83d4337!8m2!3d15.2", "action_flag": 3, "change_message": ""}}, {"model": "admin.logentry", "pk": 80, "fields": {"action_time": "2024-02-02T06:45:05.897Z", "user": 1, "content_type": 7, "object_id": "7", "object_repr": "location https://www.google.co.th/maps/place/%E0%B9%80%E0%B8%AA%E0%B8%B2%E0%B9%80%E0%B8%89%E0%B8%A5%E0%B8%B5%E0%B8%A2%E0%B8%87/data=!4m7!3m6!1s0x3115b0b2954331b5:0xd504bb3831bb08c4!8m2!3d15.404401!4d1", "action_flag": 3, "change_message": ""}}, {"model": "admin.logentry", "pk": 81, "fields": {"action_time": "2024-02-02T06:45:05.902Z", "user": 1, "content_type": 7, "object_id": "6", "object_repr": "location https://www.google.co.th/maps/place/%E0%B8%9E%E0%B8%B4%E0%B8%9E%E0%B8%B4%E0%B8%98%E0%B8%A0%E0%B8%B1%E0%B8%93%E0%B8%91%E0%B8%AA%E0%B8%96%E0%B8%B2%E0%B8%99%E0%B9%81%E0%B8%AB%E0%B9%88%E0%B8%87%E", "action_flag": 3, "change_message": ""}}, {"model": "admin.logentry", "pk": 82, "fields": {"action_time": "2024-02-02T06:45:05.907Z", "user": 1, "content_type": 7, "object_id": "5", "object_repr": "location https://www.google.co.th/maps/place/%E0%B8%AD%E0%B8%B8%E0%B8%97%E0%B8%A2%E0%B8%B2%E0%B8%99%E0%B8%99%E0%B8%B2%E0%B8%84%E0%B8%A7%E0%B8%B1%E0%B8%95%E0%B8%A3+%E0%B8%AD%E0%B8%B8%E0%B8%9A%E0%B8%A5%", "action_flag": 3, "change_message": ""}}, {"model": "admin.logentry", "pk": 83, "fields": {"action_time": "2024-02-02T06:45:05.913Z", "user": 1, "content_type": 7, "object_id": "4", "object_repr": "location https://www.google.co.th/maps/place/%E0%B8%A7%E0%B8%B1%E0%B8%94%E0%B8%9E%E0%B8%A3%E0%B8%B0%E0%B8%98%E0%B8%B2%E0%B8%95%E0%B8%B8%E0%B8%AB%E0%B8%99%E0%B8%AD%E0%B8%87%E0%B8%9A%E0%B8%B1%E0%B8%A7/d", "action_flag": 3, "change_message": ""}}, {"model": "admin.logentry", "pk": 84, "fields": {"action_time": "2024-02-02T06:45:05.917Z", "user": 1, "content_type": 7, "object_id": "3", "object_repr": "location https://www.google.co.th/maps/place/%E0%B8%97%E0%B8%B8%E0%B9%88%E0%B8%87%E0%B8%A8%E0%B8%A3%E0%B8%B5%E0%B9%80%E0%B8%A1%E0%B8%B7%E0%B8%AD%E0%B8%87/data=!4m7!3m6!1s0x3116863274283c6f:0xb2113a465", "action_flag": 3, "change_message": ""}}, {"model": "auth.permission", "pk": 1, "fields": {"name": "Can add log entry", "content_type": 1, "codename": "add_logentry"}}, {"model": "auth.permission", "pk": 2, "fields": {"name": "Can change log entry", "content_type": 1, "codename": "change_logentry"}}, {"model": "auth.permission", "pk": 3, "fields": {"name": "Can delete log entry", "content_type": 1, "codename": "delete_logentry"}}, {"model": "auth.permission", "pk": 4, "fields": {"name": "Can view log entry", "content_type": 1, "codename": "view_logentry"}}, {"model": "auth.permission", "pk": 5, "fields": {"name": "Can add permission", "content_type": 2, "codename": "add_permission"}}, {"model": "auth.permission", "pk": 6, "fields": {"name": "Can change permission", "content_type": 2, "codename": "change_permission"}}, {"model": "auth.permission", "pk": 7, "fields": {"name": "Can delete permission", "content_type": 2, "codename": "delete_permission"}}, {"model": "auth.permission", "pk": 8, "fields": {"name": "Can view permission", "content_type": 2, "codename": "view_permission"}}, {"model": "auth.permission", "pk": 9, "fields": {"name": "Can add group", "content_type": 3, "codename": "add_group"}}, {"model": "auth.permission", "pk": 10, "fields": {"name": "Can change group", "content_type": 3, "codename": "change_group"}}, {"model": "auth.permission", "pk": 11, "fields": {"name": "Can delete group", "content_type": 3, "codename": "delete_group"}}, {"model": "auth.permission", "pk": 12, "fields": {"name": "Can view group", "content_type": 3, "codename": "view_group"}}, {"model": "auth.permission", "pk": 13, "fields": {"name": "Can add user", "content_type": 4, "codename": "add_user"}}, {"model": "auth.permission", "pk": 14, "fields": {"name": "Can change user", "content_type": 4, "codename": "change_user"}}, {"model": "auth.permission", "pk": 15, "fields": {"name": "Can delete user", "content_type": 4, "codename": "delete_user"}}, {"model": "auth.permission", "pk": 16, "fields": {"name": "Can view user", "content_type": 4, "codename": "view_user"}}, {"model": "auth.permission", "pk": 17, "fields": {"name": "Can add content type", "content_type": 5, "codename": "add_contenttype"}}, {"model": "auth.permission", "pk": 18, "fields": {"name": "Can change content type", "content_type": 5, "codename": "change_contenttype"}}, {"model": "auth.permission", "pk": 19, "fields": {"name": "Can delete content type", "content_type": 5, "codename": "delete_contenttype"}}, {"model": "auth.permission", "pk": 20, "fields": {"name": "Can view content type", "content_type": 5, "codename": "view_contenttype"}}, {"model": "auth.permission", "pk": 21, "fields": {"name": "Can add session", "content_type": 6, "codename": "add_session"}}, {"model": "auth.permission", "pk": 22, "fields": {"name": "Can change session", "content_type": 6, "codename": "change_session"}}, {"model": "auth.permission", "pk": 23, "fields": {"name": "Can delete session", "content_type": 6, "codename": "delete_session"}}, {"model": "auth.permission", "pk": 24, "fields": {"name": "Can view session", "content_type": 6, "codename": "view_session"}}, {"model": "auth.permission", "pk": 25, "fields": {"name": "Can add trip", "content_type": 7, "codename": "add_trip"}}, {"model": "auth.permission", "pk": 26, "fields": {"name": "Can change trip", "content_type": 7, "codename": "change_trip"}}, {"model": "auth.permission", "pk": 27, "fields": {"name": "Can delete trip", "content_type": 7, "codename": "delete_trip"}}, {"model": "auth.permission", "pk": 28, "fields": {"name": "Can view trip", "content_type": 7, "codename": "view_trip"}}, {"model": "auth.user", "pk": 1, "fields": {"password": "pbkdf2_sha256$600000$rpaCrDNsfzgvsi7YDnGtm7$dcxxuMuCgDlg3wlRLB+TWNY6JzMpmhPnG8AswJ+cx5Q=", "last_login": "2024-02-02T07:11:31.864Z", "is_superuser": true, "username": "admin", "first_name": "", "last_name": "", "email": "", "is_staff": true, "is_active": true, "date_joined": "2023-12-18T06:52:24.996Z", "groups": [], "user_permissions": []}}, {"model": "auth.user", "pk": 2, "fields": {"password": "pbkdf2_sha256$600000$cJQZg3TFWqXsV5fuBjMLRS$A02QzF/bgJxc0KJaiJmMwV4ym5AOrsbBTc3oGOpN8ts=", "last_login": "2023-12-21T03:10:38.200Z", "is_superuser": false, "username": "Beam", "first_name": "ccc", "last_name": "vvvv", "email": "chitipat05@gmail.com", "is_staff": false, "is_active": true, "date_joined": "2023-12-18T08:01:43.525Z", "groups": [], "user_permissions": []}}, {"model": "auth.user", "pk": 3, "fields": {"password": "pbkdf2_sha256$600000$9W9TEcosSuMZ4229pMWuZx$wSLjLHbuzVZ2l3rJnBaYaaOjOcQJ4QJljFb4tnXUIvc=", "last_login": "2023-12-21T03:08:12.270Z", "is_superuser": false, "username": "Beam1", "first_name": "ชิติพัทธ์", "last_name": "บุษบงก์", "email": "chitipat.bu.64@ubu.ac.th", "is_staff": false, "is_active": true, "date_joined": "2023-12-21T03:07:55.946Z", "groups": [], "user_permissions": []}}, {"model": "contenttypes.contenttype", "pk": 1, "fields": {"app_label": "admin", "model": "logentry"}}, {"model": "contenttypes.contenttype", "pk": 2, "fields": {"app_label": "auth", "model": "permission"}}, {"model": "contenttypes.contenttype", "pk": 3, "fields": {"app_label": "auth", "model": "group"}}, {"model": "contenttypes.contenttype", "pk": 4, "fields": {"app_label": "auth", "model": "user"}}, {"model": "contenttypes.contenttype", "pk": 5, "fields": {"app_label": "contenttypes", "model": "contenttype"}}, {"model": "contenttypes.contenttype", "pk": 6, "fields": {"app_label": "sessions", "model": "session"}}, {"model": "contenttypes.contenttype", "pk": 7, "fields": {"app_label": "TourBuddy", "model": "trip"}}, {"model": "sessions.session", "pk": "bwawyzrx14o4tzk9z7ysd2rnejd14pj5", "fields": {"session_data": ".eJxVjEEOgjAQRe_StWnSQhlw6d4zkD-dqaCmTSisjHdXEha6_e-9_zIjtnUat6rLOIs5G2dOvxsjPjTvQO7It2Jjyesys90Ve9Bqr0X0eTncv4MJdfrWbSL1IBBLn3ToQ0Jgls5716gfdEBLHBxzExMhdpSCcPBw0jsBYN4fD1I5Tg:1rVnhz:Rv_eAyVnyeVzAWVhweWX8Tqi9Hh0AhIDdr6D360xbyc", "expire_date": "2024-02-16T07:11:31.872Z"}}, {"model": "sessions.session", "pk": "mi3lk1vrbcj6ogj0jv9t87kolw8a8f0n", "fields": {"session_data": ".eJxVjMEOwiAQRP-FsyFdWxbWo3e_gSyw2KqBpLQn47_bJj3ocea9mbfyvC6jX5vMfkrqos7q9NsFjk8pO0gPLveqYy3LPAW9K_qgTd9qktf1cP8ORm7jtmaEwRFLAoloyRAjSrCdAMRMKDEIZqIegUzILkNn-y30nGAwMjj1-QLs_Te_:1rFsga:4Yrx-YUeyYHRxWeM1mTU7b63GmqDxhUFbtEN4yiLyyQ", "expire_date": "2024-01-03T09:16:16.863Z"}}, {"model": "sessions.session", "pk": "p1hb76zwes1m9wziyl8baaaatjl8czhw", "fields": {"session_data": ".eJxVjMEOwiAQRP-FsyFdWxbWo3e_gSyw2KqBpLQn47_bJj3ocea9mbfyvC6jX5vMfkrqos7q9NsFjk8pO0gPLveqYy3LPAW9K_qgTd9qktf1cP8ORm7jtmaEwRFLAoloyRAjSrCdAMRMKDEIZqIegUzILkNn-y30nGAwMjj1-QLs_Te_:1rF8Zc:7DOn4Dlrsk2xu9aSMJka0tA8PJloin9Lk9aSEOaprTQ", "expire_date": "2024-01-01T08:02:00.187Z"}}, {"model": "TourBuddy.trip", "pk": 83, "fields": {"location": "https://www.google.co.th/maps/place/%E0%B8%97%E0%B8%B8%E0%B9%88%E0%B8%87%E0%B8%A8%E0%B8%A3%E0%B8%B5%E0%B9%80%E0%B8%A1%E0%B8%B7%E0%B8%AD%E0%B8%87/data=!4m7!3m6!1s0x3116863274283c6f:0xb2113a465814883a!8m2!3d15.2302166!4d104.8572949!16s%2Fg%2F11b60t_p5g!19sChIJbzwodDKGFjEROogUWEY6EbI?authuser=0&hl=th&rclk=1", "latitude": 15.2302166, "longitude": 104.8572949, "name": "ทุ่งศรีเมือง", "rating": 4.5, "review": "(3,241)", "trip_type": "สถานที่ท่องเที่ยว", "image": "https://lh5.googleusercontent.com/p/AF1QipNGNWLWRAr0f5uCaiflC8qNFrYCaIipfc_fhjr0=w138-h92-k-no"}}, {"model": "TourBuddy.trip", "pk": 84, "fields": {"location": "https://www.google.co.th/maps/place/%E0%B8%A7%E0%B8%B1%E0%B8%94%E0%B8%9E%E0%B8%A3%E0%B8%B0%E0%B8%98%E0%B8%B2%E0%B8%95%E0%B8%B8%E0%B8%AB%E0%B8%99%E0%B8%AD%E0%B8%87%E0%B8%9A%E0%B8%B1%E0%B8%A7/data=!4m7!3m6!1s0x3116880eb9d2d9a5:0x812ea3aa9150a7b!8m2!3d15.2633094!4d104.8390129!16s%2Fg%2F1thmhfrk!19sChIJpdnSuQ6IFjERewoVqTrqEgg?authuser=0&hl=th&rclk=1", "latitude": 15.2633094, "longitude": 104.8390129, "name": "วัดพระธาตุหนองบัว", "rating": 4.7, "review": "(4,092)", "trip_type": "สถานที่ท่องเที่ยว", "image": "https://lh5.googleusercontent.com/p/AF1QipMM_xtLiuUX0dtEroJHx5M6azMI224nZlR8rG2S=w80-h106-k-no"}}, {"model": "TourBuddy.trip", "pk": 85, "fields": {"location": "https://www.google.co.th/maps/place/%E0%B8%AD%E0%B8%B8%E0%B8%97%E0%B8%A2%E0%B8%B2%E0%B8%99%E0%B8%99%E0%B8%B2%E0%B8%84%E0%B8%A7%E0%B8%B1%E0%B8%95%E0%B8%A3+%E0%B8%AD%E0%B8%B8%E0%B8%9A%E0%B8%A5%E0%B8%A3%E0%B8%B2%E0%B8%8A%E0%B8%98%E0%B8%B2%E0%B8%99%E0%B8%B5/data=!4m7!3m6!1s0x31168b778531c12b:0x55f2a0ab6e8c950a!8m2!3d15.2539867!4d104.705919!16s%2Fg%2F11fm4jrh6_!19sChIJK8ExhXeLFjERCpWMbqug8lU?authuser=0&hl=th&rclk=1", "latitude": 15.2539867, "longitude": 104.705919, "name": "อุทยานนาควัตร อุบลราชธานี", "rating": 4.4, "review": "(341)", "trip_type": "สถานที่ท่องเที่ยว", "image": "https://lh5.googleusercontent.com/p/AF1QipPKfgCDKZq5tPcZYR2-lzjjrL7xrp7b_ZNXjmn8=w122-h92-k-no"}}, {"model": "TourBuddy.trip", "pk": 86, "fields": {"location": "https://www.google.co.th/maps/place/%E0%B8%9E%E0%B8%B4%E0%B8%9E%E0%B8%B4%E0%B8%98%E0%B8%A0%E0%B8%B1%E0%B8%93%E0%B8%91%E0%B8%AA%E0%B8%96%E0%B8%B2%E0%B8%99%E0%B9%81%E0%B8%AB%E0%B9%88%E0%B8%87%E0%B8%8A%E0%B8%B2%E0%B8%95%E0%B8%B4%E0%B8%AD%E0%B8%B8%E0%B8%9A%E0%B8%A5%E0%B8%A3%E0%B8%B2%E0%B8%8A%E0%B8%98%E0%B8%B2%E0%B8%99%E0%B8%B5/data=!4m7!3m6!1s0x31168631faf5ff05:0xd86aab90ff2c770a!8m2!3d15.2277845!4d104.85762!16s%2Fg%2F1tksktv_!19sChIJBf_1-jGGFjERCncs_5Cratg?authuser=0&hl=th&rclk=1", "latitude": 15.2277845, "longitude": 104.85762, "name": "พิพิธภัณฑสถานแห่งชาติอุบลราชธานี", "rating": 4.5, "review": "(353)", "trip_type": "สถานที่ท่องเที่ยว", "image": "https://lh5.googleusercontent.com/p/AF1QipMmfRlPtIw2cuLGufI1VfiMPLGxkiiwagSbhcbk=w80-h106-k-no"}}, {"model": "TourBuddy.trip", "pk": 87, "fields": {"location": "https://www.google.co.th/maps/place/%E0%B9%80%E0%B8%AA%E0%B8%B2%E0%B9%80%E0%B8%89%E0%B8%A5%E0%B8%B5%E0%B8%A2%E0%B8%87/data=!4m7!3m6!1s0x3115b0b2954331b5:0xd504bb3831bb08c4!8m2!3d15.404401!4d105.5020614!16s%2Fg%2F1vvyvjnt!19sChIJtTFDlbKwFTERxAi7MTi7BNU?authuser=0&hl=th&rclk=1", "latitude": 15.404401, "longitude": 105.5020614, "name": "เสาเฉลียง", "rating": 4.4, "review": "(635)", "trip_type": "สถานที่ท่องเที่ยว", "image": "https://lh5.googleusercontent.com/p/AF1QipNtBYGxmitqahergUnQou60Sl-oEPA2aGGAW5cW=w138-h92-k-no"}}, {"model": "TourBuddy.trip", "pk": 88, "fields": {"location": "https://www.google.co.th/maps/place/%E0%B8%AB%E0%B8%B2%E0%B8%94%E0%B8%84%E0%B8%B9%E0%B9%80%E0%B8%94%E0%B8%B7%E0%B9%88%E0%B8%AD/data=!4m7!3m6!1s0x311689215d6532b1:0xb2e2cf45d83d4337!8m2!3d15.2110538!4d104.7935284!16s%2Fg%2F11ckvvj8g6!19sChIJsTJlXSGJFjERN0M92EXP4rI?authuser=0&hl=th&rclk=1", "latitude": 15.2110538, "longitude": 104.7935284, "name": "หาดคูเดื่อ", "rating": 4.2, "review": "(1,515)", "trip_type": "สถานที่ท่องเที่ยว", "image": "https://lh5.googleusercontent.com/p/AF1QipMRm6oapoq3KtxD8peRoF-HAwgfsd7qWiwenCis=w122-h92-k-no"}}, {"model": "TourBuddy.trip", "pk": 89, "fields": {"location": "https://www.google.co.th/maps/place/%E0%B9%80%E0%B8%97%E0%B8%B5%E0%B9%88%E0%B8%A2%E0%B8%A7%E0%B8%88%E0%B8%B1%E0%B8%87%E0%B8%AB%E0%B8%A7%E0%B8%B1%E0%B8%94%E0%B8%AD%E0%B8%B8%E0%B8%9A%E0%B8%A5%E0%B8%A3%E0%B8%B2%E0%B8%8A%E0%B8%98%E0%B8%B2%E0%B8%99%E0%B8%B5/data=!4m7!3m6!1s0x31168730c4d64767:0x9ac5c81a88829b99!8m2!3d15.2730179!4d104.8466846!16s%2Fg%2F11tjyw2vtg!19sChIJZ0fWxDCHFjERmZuCiBrIxZo?authuser=0&hl=th&rclk=1", "latitude": 15.2730179, "longitude": 104.8466846, "name": "เที่ยวจังหวัดอุบลราชธานี", "rating": null, "review": "", "trip_type": "สถานที่ท่องเที่ยว", "image": "https://streetviewpixels-pa.googleapis.com/v1/thumbnail?panoid=GJE5vehW2-P56vDS2HIh0Q&cb_client=search.gws-prod.gps&w=80&h=92&yaw=139.01535&pitch=0&thumbfov=100"}}, {"model": "TourBuddy.trip", "pk": 90, "fields": {"location": "https://www.google.co.th/maps/place/%E0%B8%AB%E0%B8%B2%E0%B8%94%E0%B8%8A%E0%B8%A1%E0%B8%94%E0%B8%B2%E0%B8%A7,+%E0%B9%81%E0%B8%81%E0%B9%88%E0%B8%87%E0%B8%8A%E0%B8%A1%E0%B8%94%E0%B8%B2%E0%B8%A7/data=!4m7!3m6!1s0x3115f46a09abcbfb:0x99cbda8fafe21a76!8m2!3d15.9074971!4d105.3414416!16s%2Fg%2F11g0gddyk4!19sChIJ-8urCWr0FTERdhrir4_ay5k?authuser=0&hl=th&rclk=1", "latitude": 15.9074971, "longitude": 105.3414416, "name": "หาดชมดาว, แก่งชมดาว", "rating": 4.3, "review": "(357)", "trip_type": "สถานที่ท่องเที่ยว", "image": "https://lh5.googleusercontent.com/p/AF1QipMnGSW82KYkWMRBtLVETG__ZM-CZBdJqdk-ojlX=w122-h92-k-no"}}, {"model": "TourBuddy.trip", "pk": 91, "fields": {"location": "https://www.google.co.th/maps/place/%E0%B8%9E%E0%B8%B1%E0%B8%97%E0%B8%A2%E0%B8%B2%E0%B8%99%E0%B9%89%E0%B8%AD%E0%B8%A2+%E0%B8%AD%E0%B8%B8%E0%B8%9A%E0%B8%A5%E0%B8%A3%E0%B8%B2%E0%B8%8A%E0%B8%98%E0%B8%B2%E0%B8%99%E0%B8%B5/data=!4m7!3m6!1s0x31143435072572d7:0x26475ddd81ca393!8m2!3d15.1742416!4d105.3585877!16s%2Fg%2F11b7d_s_3w!19sChIJ13IlBzU0FDERk6Mc2N11ZAI?authuser=0&hl=th&rclk=1", "latitude": 15.1742416, "longitude": 105.3585877, "name": "พัทยาน้อย อุบลราชธานี", "rating": 4.3, "review": "(2,203)", "trip_type": "สถานที่ท่องเที่ยว", "image": "https://lh5.googleusercontent.com/p/AF1QipMRoFcqB8Dci2ihwOkcSFRvu6HCyKJ8kL_FjydT=w122-h92-k-no"}}, {"model": "TourBuddy.trip", "pk": 92, "fields": {"location": "https://www.google.co.th/maps/place/%E0%B8%82%E0%B8%B1%E0%B8%A7%E0%B8%99%E0%B9%89%E0%B8%AD%E0%B8%A2%E0%B8%9A%E0%B9%89%E0%B8%B2%E0%B8%99%E0%B8%8A%E0%B8%B5%E0%B8%97%E0%B8%A7%E0%B8%99/data=!4m7!3m6!1s0x31168aab30beac27:0x22ee1eb6241c0f36!8m2!3d15.2889021!4d104.6594199!16s%2Fg%2F11hbhsnzdc!19sChIJJ6y-MKuKFjERNg8cJLYe7iI?authuser=0&hl=th&rclk=1", "latitude": 15.2889021, "longitude": 104.6594199, "name": "ขัวน้อยบ้านชีทวน", "rating": 4.3, "review": "(306)", "trip_type": "สถานที่ท่องเที่ยว", "image": "https://lh5.googleusercontent.com/p/AF1QipNKlG6GP8QkaLeG6MSrK2xepBayvi83id-nuCDN=w80-h106-k-no"}}, {"model": "TourBuddy.trip", "pk": 93, "fields": {"location": "https://www.google.co.th/maps/place/%E0%B8%A7%E0%B8%B1%E0%B8%94%E0%B8%97%E0%B8%B8%E0%B9%88%E0%B8%87%E0%B8%A8%E0%B8%A3%E0%B8%B5%E0%B9%80%E0%B8%A1%E0%B8%B7%E0%B8%AD%E0%B8%87/data=!4m7!3m6!1s0x31168633a5b99843:0x582858e1b4f0420a!8m2!3d15.2297025!4d104.8611318!16s%2Fg%2F1tgf9twj!19sChIJQ5i5pTOGFjERCkLwtOFYKFg?authuser=0&hl=th&rclk=1", "latitude": 15.2297025, "longitude": 104.8611318, "name": "วัดทุ่งศรีเมือง", "rating": 4.3, "review": "(674)", "trip_type": "สถานที่ท่องเที่ยว", "image": "https://lh5.googleusercontent.com/p/AF1QipNATVnflqSRoC5p4GEGYO8laDBO9Ey4qio9gdt5=w122-h92-k-no"}}, {"model": "TourBuddy.trip", "pk": 94, "fields": {"location": "https://www.google.co.th/maps/place/%E0%B8%97%E0%B8%B8%E0%B9%88%E0%B8%87%E0%B8%94%E0%B8%AD%E0%B8%81%E0%B8%AB%E0%B8%8D%E0%B9%89%E0%B8%B2+%28%E0%B8%AB%E0%B8%99%E0%B8%AD%E0%B8%87%E0%B8%AB%E0%B8%8D%E0%B9%89%E0%B8%B2%E0%B8%A1%E0%B9%89%E0%B8%B2%29+%E0%B8%AD%E0%B8%B8%E0%B8%9A%E0%B8%A5%E0%B8%A3%E0%B8%B2%E0%B8%8A%E0%B8%98%E0%B8%B2%E0%B8%99%E0%B8%B5/data=!4m7!3m6!1s0x311683f6e72460c7:0x80fa33b7718613dc!8m2!3d15.1678694!4d104.9431164!16s%2Fg%2F11d_y8kx6w!19sChIJx2Ak5_aDFjER3BOGcbcz-oA?authuser=0&hl=th&rclk=1", "latitude": 15.1678694, "longitude": 104.9431164, "name": "ทุ่งดอกหญ้า (หนองหญ้าม้า) อุบลราชธานี", "rating": 4.8, "review": "(17)", "trip_type": "สถานที่ท่องเที่ยว", "image": "https://lh5.googleusercontent.com/p/AF1QipMS-CajaAiSBhRO1Eu5bCf1aY2Ekeg2G0SH2VoF=w138-h92-k-no"}}, {"model": "TourBuddy.trip", "pk": 95, "fields": {"location": "https://www.google.co.th/maps/place/%E0%B9%80%E0%B8%82%E0%B8%B7%E0%B9%88%E0%B8%AD%E0%B8%99%E0%B8%AA%E0%B8%B4%E0%B8%A3%E0%B8%B4%E0%B8%99%E0%B8%98%E0%B8%A3/data=!4m7!3m6!1s0x31144a92a6b593b5:0x2cfc58d833ddcc49!8m2!3d15.2055!4d105.4301748!16s%2Fm%2F0g5prgp!19sChIJtZO1ppJKFDERSczdM9hY_Cw?authuser=0&hl=th&rclk=1", "latitude": 15.2055, "longitude": 105.4301748, "name": "เขื่อนสิรินธร", "rating": 4.4, "review": "(560)", "trip_type": "สถานที่ท่องเที่ยว", "image": "https://lh5.googleusercontent.com/p/AF1QipMfFK7mcNWND9qcOMK6HBGA6Yrc4uNqlel-8qDr=w122-h92-k-no"}}, {"model": "TourBuddy.trip", "pk": 96, "fields": {"location": "https://www.google.co.th/maps/place/%E0%B8%99%E0%B9%89%E0%B8%B3%E0%B8%95%E0%B8%81%E0%B8%AA%E0%B8%A3%E0%B9%89%E0%B8%AD%E0%B8%A2%E0%B8%AA%E0%B8%A7%E0%B8%A3%E0%B8%A3%E0%B8%84%E0%B9%8C/data=!4m7!3m6!1s0x3115bb216572474d:0x3b93352091ac6670!8m2!3d15.4599678!4d105.578091!16s%2Fg%2F1tgz7tdw!19sChIJTUdyZSG7FTERcGaskSA1kzs?authuser=0&hl=th&rclk=1", "latitude": 15.4599678, "longitude": 105.578091, "name": "น้ำตกสร้อยสวรรค์", "rating": 4.4, "review": "(350)", "trip_type": "สถานที่ท่องเที่ยว", "image": "https://lh5.googleusercontent.com/p/AF1QipOLEte6Rxo9lRbd7M_Ed3i3zqdtsoch2QeOAnY5=w130-h92-k-no"}}, {"model": "TourBuddy.trip", "pk": 97, "fields": {"location": "https://www.google.co.th/maps/place/%E0%B8%AA%E0%B8%B2%E0%B8%A1%E0%B8%9E%E0%B8%B1%E0%B8%99%E0%B9%82%E0%B8%9A%E0%B8%81/data=!4m7!3m6!1s0x3115ed1aaaaaaaab:0xeefee5c8280563c2!8m2!3d15.7970209!4d105.3965754!16s%2Fg%2F1hm5hng7j!19sChIJq6qqqhrtFTERwmMFKMjl_u4?authuser=0&hl=th&rclk=1", "latitude": 15.7970209, "longitude": 105.3965754, "name": "สามพันโบก", "rating": 4.5, "review": "(1,623)", "trip_type": "สถานที่ท่องเที่ยว", "image": "https://lh5.googleusercontent.com/p/AF1QipPijlz7e_CG0hA1wjfgiY_3Gin6DLosK2WEu-se=w163-h92-k-no"}}, {"model": "TourBuddy.trip", "pk": 98, "fields": {"location": "https://www.google.co.th/maps/place/%E0%B8%97%E0%B8%B8%E0%B9%88%E0%B8%87%E0%B8%94%E0%B8%AD%E0%B8%81%E0%B8%97%E0%B8%B2%E0%B8%99%E0%B8%95%E0%B8%B0%E0%B8%A7%E0%B8%B1%E0%B8%99+%E0%B8%9A%E0%B9%89%E0%B8%B2%E0%B8%99%E0%B8%81%E0%B9%88%E0%B8%AD/data=!4m7!3m6!1s0x311685a2e55c7bad:0xeebe7c77b3b2041e!8m2!3d15.1447089!4d104.8561525!16s%2Fg%2F11j2_zx1y8!19sChIJrXtc5aKFFjERHgSys3d8vu4?authuser=0&hl=th&rclk=1", "latitude": 15.1447089, "longitude": 104.8561525, "name": "ทุ่งดอกทานตะวัน บ้านก่อ", "rating": 4.5, "review": "(61)", "trip_type": "สถานที่ท่องเที่ยว", "image": "https://lh5.googleusercontent.com/p/AF1QipMJ0ptraq92I5VAFcTKZqMnlKbaDuY-OXBA2cQj=w138-h92-k-no"}}, {"model": "TourBuddy.trip", "pk": 99, "fields": {"location": "https://www.google.co.th/maps/place/%E0%B8%9B%E0%B9%88%E0%B8%B2%E0%B8%94%E0%B8%87%E0%B8%99%E0%B8%B2%E0%B8%97%E0%B8%B2%E0%B8%A1/data=!4m7!3m6!1s0x3115bd9d7fc1cddb:0x3d3948b9d64a5e8e!8m2!3d15.5819837!4d105.5473585!16s%2Fg%2F1hm3b727p!19sChIJ283Bf529FTERjl5K1rlIOT0?authuser=0&hl=th&rclk=1", "latitude": 15.5819837, "longitude": 105.5473585, "name": "ป่าดงนาทาม", "rating": 4.5, "review": "(36)", "trip_type": "สถานที่ท่องเที่ยว", "image": "https://lh5.googleusercontent.com/p/AF1QipMObN6h51S6KAAiXnRveW_JMg1Cb4oi3_XWASsg=w122-h92-k-no"}}, {"model": "TourBuddy.trip", "pk": 100, "fields": {"location": "https://www.google.co.th/maps/place/%E0%B8%99%E0%B9%89%E0%B8%B3%E0%B8%95%E0%B8%81%E0%B8%97%E0%B8%B8%E0%B9%88%E0%B8%87%E0%B8%99%E0%B8%B2%E0%B9%80%E0%B8%A1%E0%B8%B7%E0%B8%AD%E0%B8%87/data=!4m7!3m6!1s0x3115a332c16ff411:0x771de7141a2fbcc0!8m2!3d15.5326997!4d105.5967221!16s%2Fg%2F1vhq14yj!19sChIJEfRvwTKjFTERwLwvGhTnHXc?authuser=0&hl=th&rclk=1", "latitude": 15.5326997, "longitude": 105.5967221, "name": "น้ำตกทุ่งนาเมือง", "rating": 4.3, "review": "(112)", "trip_type": "สถานที่ท่องเที่ยว", "image": "https://lh5.googleusercontent.com/p/AF1QipPqlrcf2VKPrdwdeRsoHDdEl5A1P6n6VvOzEDcL=w138-h92-k-no"}}, {"model": "TourBuddy.trip", "pk": 101, "fields": {"location": "https://www.google.co.th/maps/place/%E0%B8%94%E0%B8%AD%E0%B8%81%E0%B8%AD%E0%B9%89%E0%B8%AD%E0%B8%97%E0%B8%B8%E0%B9%88%E0%B8%87%E0%B8%99%E0%B8%B2%E0%B8%9B%E0%B9%88%E0%B8%B2%E0%B8%9A%E0%B8%B1%E0%B8%A7/data=!4m7!3m6!1s0x31169b6822c816d9:0xc7ea4f2cc0883fef!8m2!3d15.0925992!4d104.897143!16s%2Fg%2F11td0jx4w1!19sChIJ2RbIImibFjER7z-IwCxP6sc?authuser=0&hl=th&rclk=1", "latitude": 15.0925992, "longitude": 104.897143, "name": "ดอกอ้อทุ่งนาป่าบัว", "rating": null, "review": "", "trip_type": "สถานที่ท่องเที่ยว", "image": "https://lh5.googleusercontent.com/p/AF1QipNmIIRGTXtzd37RbkYK6ywnZprFscKnIeKrXIl1=w122-h92-k-no"}}, {"model": "TourBuddy.trip", "pk": 102, "fields": {"location": "https://www.google.co.th/maps/place/Graffiti+wall/data=!4m7!3m6!1s0x311687290d089905:0x97f4a58fee5155a8!8m2!3d15.2259389!4d104.8674571!16s%2Fg%2F11fnpldtm6!19sChIJBZkIDSmHFjERqFVR7o-l9Jc?authuser=0&hl=th&rclk=1", "latitude": 15.2259389, "longitude": 104.8674571, "name": "Graffiti wall", "rating": 3.5, "review": "(6)", "trip_type": "สถานที่ท่องเที่ยว", "image": "https://lh5.googleusercontent.com/p/AF1QipMNSfGRMgVl97cOYryc1MyZT3bbbsxrqDJ-HnHD=w194-h92-k-no"}}, {"model": "TourBuddy.trip", "pk": 103, "fields": {"location": "https://www.google.co.th/maps/place/%E0%B8%A0%E0%B8%B2%E0%B8%9E%E0%B9%80%E0%B8%82%E0%B8%B5%E0%B8%A2%E0%B8%99%E0%B8%AA%E0%B8%B5+%28%E0%B8%9C%E0%B8%B2%E0%B8%AB%E0%B8%A1%E0%B8%AD%E0%B8%99%E0%B8%99%E0%B9%89%E0%B8%AD%E0%B8%A2%29/data=!4m7!3m6!1s0x3115b0b0acbc1839:0xca48d51b03b68769!8m2!3d15.3994349!4d105.5118369!16s%2Fg%2F1hm4bwd80!19sChIJORi8rLCwFTERaYe2AxvVSMo?authuser=0&hl=th&rclk=1", "latitude": 15.3994349, "longitude": 105.5118369, "name": "ภาพเขียนสี (ผาหมอนน้อย)", "rating": 4.6, "review": "(77)", "trip_type": "สถานที่ท่องเที่ยว", "image": "https://lh5.googleusercontent.com/p/AF1QipPh4KnkjcV4yTh2BJXr-VoBSApbR1CLihTWoTRd=w122-h92-k-no"}}, {"model": "TourBuddy.trip", "pk": 104, "fields": {"location": "https://www.google.co.th/maps/place/%E0%B8%A7%E0%B8%B1%E0%B8%94%E0%B8%96%E0%B9%89%E0%B8%B3%E0%B8%84%E0%B8%B9%E0%B8%AB%E0%B8%B2%E0%B8%AA%E0%B8%A7%E0%B8%A3%E0%B8%A3%E0%B8%84%E0%B9%8C+%E0%B8%AD%E0%B8%B8%E0%B8%9A%E0%B8%A5%E0%B8%A3%E0%B8%B2%E0%B8%8A%E0%B8%98%E0%B8%B2%E0%B8%99%E0%B8%B5/data=!4m7!3m6!1s0x3115b41cb1f5482b:0x4e53925104051be3!8m2!3d15.3227164!4d105.4877705!16s%2Fg%2F1tgn71y9!19sChIJK0j1sRy0FTER4xsFBFGSU04?authuser=0&hl=th&rclk=1", "latitude": 15.3227164, "longitude": 105.4877705, "name": "วัดถ้ำคูหาสวรรค์ อุบลราชธานี", "rating": 4.5, "review": "(2,242)", "trip_type": "สถานที่ท่องเที่ยว", "image": "https://lh5.googleusercontent.com/p/AF1QipPfN2pb3Imdc-nOGBXLnB8_b6RNBJyXvwaPBcjx=w138-h92-k-no"}}, {"model": "TourBuddy.trip", "pk": 105, "fields": {"location": "https://www.google.co.th/maps/place/%E0%B8%AB%E0%B8%B2%E0%B8%94%E0%B8%AB%E0%B8%87%E0%B8%AA%E0%B9%8C/data=!4m7!3m6!1s0x31158d2eec745c4d:0x2fec22138d3a2209!8m2!3d15.792802!4d105.4110691!16s%2Fg%2F11flgdqgp6!19sChIJTVx07C6NFTERCSI6jRMi7C8?authuser=0&hl=th&rclk=1", "latitude": 15.792802, "longitude": 105.4110691, "name": "หาดหงส์", "rating": 4.4, "review": "(18)", "trip_type": "สถานที่ท่องเที่ยว", "image": "https://lh5.googleusercontent.com/p/AF1QipPBI3_vaiMbH7M8skBYqBmYfsUnq_RyGbe_Bdj1=w122-h92-k-no"}}, {"model": "TourBuddy.trip", "pk": 106, "fields": {"location": "https://www.google.co.th/maps/place/%E0%B8%99%E0%B9%89%E0%B8%B3%E0%B8%95%E0%B8%81%E0%B9%82%E0%B8%9A%E0%B8%81%E0%B8%A5%E0%B8%B6%E0%B8%81/data=!4m7!3m6!1s0x3115be52a1e5ab87:0x30f76b949df6c44e!8m2!3d15.5365937!4d105.4025803!16s%2Fg%2F11cr_7d2d3!19sChIJh6vloVK-FTERTsT2nZRr9zA?authuser=0&hl=th&rclk=1", "latitude": 15.5365937, "longitude": 105.4025803, "name": "น้ำตกโบกลึก", "rating": 4.3, "review": "(30)", "trip_type": "สถานที่ท่องเที่ยว", "image": "https://lh5.googleusercontent.com/p/AF1QipNMNG9qPhHH2yYq7yGqiang3P0wzsE3gai54yo=w122-h92-k-no"}}, {"model": "TourBuddy.trip", "pk": 107, "fields": {"location": "https://www.google.co.th/maps/place/%E0%B8%9A%E0%B9%88%E0%B8%AD+%E0%B8%81%E0%B8%B0%E0%B9%81%E0%B8%A1%E0%B8%94/data=!4m7!3m6!1s0x31168547cc7a99eb:0xf227a7e2175cef63!8m2!3d15.1088138!4d104.9163746!16s%2Fg%2F11sjrgp7b9!19sChIJ65l6zEeFFjERY-9cF-KnJ_I?authuser=0&hl=th&rclk=1", "latitude": 15.1088138, "longitude": 104.9163746, "name": "บ่อ กะแมด", "rating": 5.0, "review": "(1)", "trip_type": "สถานที่ท่องเที่ยว", "image": "https://lh5.googleusercontent.com/p/AF1QipMLaaAzfNr_7_BOhhS6KXenBDztBKYMeLVlSban=w80-h106-k-no"}}, {"model": "TourBuddy.trip", "pk": 108, "fields": {"location": "https://www.google.co.th/maps/place/%E0%B8%A7%E0%B8%B1%E0%B8%94%E0%B8%AB%E0%B8%99%E0%B8%AD%E0%B8%87%E0%B8%9B%E0%B9%88%E0%B8%B2%E0%B8%9E%E0%B8%87+%28%E0%B8%AB%E0%B8%A5%E0%B8%A7%E0%B8%87%E0%B8%9B%E0%B8%B9%E0%B9%88%E0%B8%8A%E0%B8%B2%29/data=!4m7!3m6!1s0x31168f6e63dd2acd:0x5dd98ff4dadec21a!8m2!3d15.1587969!4d104.828953!16s%2Fm%2F04cyclf!19sChIJzSrdY26PFjERGsLe2vSP2V0?authuser=0&hl=th&rclk=1", "latitude": 15.1587969, "longitude": 104.828953, "name": "วัดหนองป่าพง (หลวงปู่ชา)", "rating": 4.8, "review": "(959)", "trip_type": "สถานที่ท่องเที่ยว", "image": "https://lh5.googleusercontent.com/p/AF1QipOsKOgQpuuS4rNpCpzRsiGOq5jExPfuNkKQJmNN=w122-h92-k-no"}}, {"model": "TourBuddy.trip", "pk": 109, "fields": {"location": "https://www.google.co.th/maps/place/%E0%B8%AD%E0%B9%88%E0%B8%B2%E0%B8%87%E0%B9%80%E0%B8%81%E0%B9%87%E0%B8%9A%E0%B8%99%E0%B9%89%E0%B8%B3%E0%B8%AB%E0%B9%89%E0%B8%A7%E0%B8%A2%E0%B9%81%E0%B8%88%E0%B8%A3%E0%B8%B0%E0%B9%81%E0%B8%A1/data=!4m7!3m6!1s0x3116890215f9b925:0xc50af43b12d47d82!8m2!3d15.2788002!4d104.807804!16s%2Fg%2F11gjt_lglw!19sChIJJbn5FQKJFjERgn3UEjv0CsU?authuser=0&hl=th&rclk=1", "latitude": 15.2788002, "longitude": 104.807804, "name": "อ่างเก็บน้ำห้วยแจระแม", "rating": 5.0, "review": "(3)", "trip_type": "สถานที่ท่องเที่ยว", "image": "https://lh5.googleusercontent.com/p/AF1QipNk9-oHTLqAupCsIgPsfeVK3QrkevUXGHb_nbs=w122-h92-k-no"}}, {"model": "TourBuddy.trip", "pk": 110, "fields": {"location": "https://www.google.co.th/maps/place/%E0%B8%A8%E0%B8%B9%E0%B8%99%E0%B8%A2%E0%B9%8C%E0%B8%A8%E0%B8%B4%E0%B8%A5%E0%B8%9B%E0%B8%A7%E0%B8%B1%E0%B8%92%E0%B8%99%E0%B8%98%E0%B8%A3%E0%B8%A3%E0%B8%A1%E0%B8%81%E0%B8%B2%E0%B8%8D%E0%B8%88%E0%B8%99%E0%B8%B2%E0%B8%A0%E0%B8%B4%E0%B9%80%E0%B8%A9%E0%B8%81%E0%B8%AD%E0%B8%B8%E0%B8%9A%E0%B8%A5%E0%B8%A3%E0%B8%B2%E0%B8%8A%E0%B8%98%E0%B8%B2%E0%B8%99%E0%B8%B5/data=!4m7!3m6!1s0x31168877fd891839:0xc8d0fadf6d782ee1!8m2!3d15.2466906!4d104.8457472!16s%2Fg%2F1tg4ywj9!19sChIJORiJ_XeIFjER4S54bd_60Mg?authuser=0&hl=th&rclk=1", "latitude": 15.2466906, "longitude": 104.8457472, "name": "ศูนย์ศิลปวัฒนธรรมกาญจนาภิเษกอุบลราชธานี", "rating": 4.3, "review": "(42)", "trip_type": "สถานที่ท่องเที่ยว", "image": "https://lh5.googleusercontent.com/p/AF1QipPx9qFkkpjZGY3Xajv8X6G0Zv8uP-CVfZhTU1oR=w122-h92-k-no"}}, {"model": "TourBuddy.trip", "pk": 111, "fields": {"location": "https://www.google.co.th/maps/place/%E0%B8%99%E0%B9%89%E0%B8%B3%E0%B8%95%E0%B8%81%E0%B9%81%E0%B8%AA%E0%B8%87%E0%B8%88%E0%B8%B1%E0%B8%99%E0%B8%97%E0%B8%A3%E0%B9%8C+%28%E0%B8%99%E0%B9%89%E0%B8%B3%E0%B8%95%E0%B8%81%E0%B8%A5%E0%B8%87%E0%B8%A3%E0%B8%B9%29/data=!4m7!3m6!1s0x3115bcb24b9060ff:0xdc127b055fe20ad1!8m2!3d15.5159063!4d105.5897133!16s%2Fg%2F1tfg0jv4!19sChIJ_2CQS7K8FTER0QriXwV7Etw?authuser=0&hl=th&rclk=1", "latitude": 15.5159063, "longitude": 105.5897133, "name": "น้ำตกแสงจันทร์ (น้ำตกลงรู)", "rating": 4.3, "review": "(556)", "trip_type": "สถานที่ท่องเที่ยว", "image": "https://lh5.googleusercontent.com/p/AF1QipMJjwVHJExGXencqXJEl_N-pEjTbzDopPm7VtRq=w163-h92-k-no"}}, {"model": "TourBuddy.trip", "pk": 112, "fields": {"location": "https://www.google.co.th/maps/place/%E0%B8%99%E0%B9%89%E0%B8%B3%E0%B8%95%E0%B8%81%E0%B8%AB%E0%B9%89%E0%B8%A7%E0%B8%A2%E0%B8%AB%E0%B8%A5%E0%B8%A7%E0%B8%87+%E0%B8%A0%E0%B8%B9%E0%B8%88%E0%B8%AD%E0%B8%87%E0%B8%99%E0%B8%B2%E0%B8%A2%E0%B8%AD%E0%B8%A2/data=!4m7!3m6!1s0x3113f7d313aca491:0xe16a37ad87d1284f!8m2!3d14.4422717!4d105.2741437!16s%2Fg%2F11qh1x72x8!19sChIJkaSsE9P3EzERTyjRh603auE?authuser=0&hl=th&rclk=1", "latitude": 14.4422717, "longitude": 105.2741437, "name": "น้ำตกห้วยหลวง ภูจองนายอย", "rating": 4.7, "review": "(313)", "trip_type": "สถานที่ท่องเที่ยว", "image": "https://lh5.googleusercontent.com/p/AF1QipO3-yBbSskeZ1KQ4jGU08Puqk1TpEnD1HGd0xsG=w139-h92-k-no"}}, {"model": "TourBuddy.trip", "pk": 113, "fields": {"location": "https://www.google.co.th/maps/place/%E0%B8%A7%E0%B8%B1%E0%B8%94%E0%B8%AA%E0%B8%B4%E0%B8%A3%E0%B8%B4%E0%B8%99%E0%B8%98%E0%B8%A3%E0%B8%A7%E0%B8%A3%E0%B8%B2%E0%B8%A3%E0%B8%B2%E0%B8%A1%E0%B8%A0%E0%B8%B9%E0%B8%9E%E0%B8%A3%E0%B9%89%E0%B8%B2%E0%B8%A7/data=!4m7!3m6!1s0x31144bd85bbdb5bb:0xc3ec0032db50ff06!8m2!3d15.1488025!4d105.4677779!16s%2Fg%2F11c1t5rpbw!19sChIJu7W9W9hLFDERBv9Q2zIA7MM?authuser=0&hl=th&rclk=1", "latitude": 15.1488025, "longitude": 105.4677779, "name": "วัดสิรินธรวรารามภูพร้าว", "rating": 4.7, "review": "(4,504)", "trip_type": "สถานที่ท่องเที่ยว", "image": "https://lh5.googleusercontent.com/p/AF1QipM4dEResxg_0DT7Ds9UvAxeyOouG0nNlzTej20b=w122-h92-k-no"}}, {"model": "TourBuddy.trip", "pk": 114, "fields": {"location": "https://www.google.co.th/maps/place/Ubon+Street+Art+-+The+Ubonratchathani/data=!4m7!3m6!1s0x31168796f10baf6f:0xa064aff7ce305361!8m2!3d15.2271084!4d104.8576992!16s%2Fg%2F11jzw8jb_y!19sChIJb68L8ZaHFjERYVMwzvevZKA?authuser=0&hl=th&rclk=1", "latitude": 15.2271084, "longitude": 104.8576992, "name": "Ubon Street Art - The Ubonratchathani", "rating": 5.0, "review": "(1)", "trip_type": "สถานที่ท่องเที่ยว", "image": "https://lh5.googleusercontent.com/p/AF1QipNkPHSMkt1X2vN6aUHH1gtp7yN-UIgYhoZ54KH1=w122-h92-k-no"}}, {"model": "TourBuddy.trip", "pk": 115, "fields": {"location": "https://www.google.co.th/maps/place/%E0%B8%9C%E0%B8%B2%E0%B8%8A%E0%B8%B1%E0%B8%99+%E0%B8%AD%E0%B8%B8%E0%B8%9A%E0%B8%A5%E0%B8%A3%E0%B8%B2%E0%B8%8A%E0%B8%98%E0%B8%B2%E0%B8%99%E0%B8%B5/data=!4m7!3m6!1s0x311592187f99f5d3:0xa3c19ee2330c7c6b!8m2!3d15.7598663!4d105.4916165!16s%2Fg%2F1hm1qh61q!19sChIJ0_WZfxiSFTERa3wMM-KewaM?authuser=0&hl=th&rclk=1", "latitude": 15.7598663, "longitude": 105.4916165, "name": "ผาชัน อุบลราชธานี", "rating": 4.4, "review": "(62)", "trip_type": "สถานที่ท่องเที่ยว", "image": "https://lh5.googleusercontent.com/p/AF1QipOHI-0_x4Xwudbv6AlScGxlCZ_WK0_DwG4k4wDs=w122-h92-k-no"}}, {"model": "TourBuddy.trip", "pk": 116, "fields": {"location": "https://www.google.co.th/maps/place/%E0%B9%81%E0%B8%81%E0%B9%88%E0%B8%87%E0%B8%AA%E0%B8%B0%E0%B8%9E%E0%B8%B7%E0%B8%AD/data=!4m7!3m6!1s0x311432c9d9705d45:0xa2dc6bdcad0c3303!8m2!3d15.2461458!4d105.242611!16s%2Fg%2F11gfh93zdt!19sChIJRV1w2ckyFDERAzMMrdxr3KI?authuser=0&hl=th&rclk=1", "latitude": 15.2461458, "longitude": 105.242611, "name": "แก่งสะพือ", "rating": 4.1, "review": "(1,271)", "trip_type": "สถานที่ท่องเที่ยว", "image": "https://lh5.googleusercontent.com/p/AF1QipMAo5DCzaEL_CjYNfpPvoVsmlM0T3N5kqj5ZSvN=w122-h92-k-no"}}, {"model": "TourBuddy.trip", "pk": 117, "fields": {"location": "https://www.google.co.th/maps/place/%E0%B8%95%E0%B8%B2%E0%B8%A1%E0%B8%A3%E0%B8%AD%E0%B8%A2%E0%B8%A0%E0%B8%B2%E0%B8%9E%E0%B8%A2%E0%B8%99%E0%B8%95%E0%B9%8C+Alexander/data=!4m7!3m6!1s0x311681454fdd53ed:0x51562ee6da08dd65!8m2!3d15.2405007!4d104.9558734!16s%2Fg%2F11tk9khtd0!19sChIJ7VPdT0WBFjERZd0I2uYuVlE?authuser=0&hl=th&rclk=1", "latitude": 15.2405007, "longitude": 104.9558734, "name": "ตามรอยภาพยนต์ Alexander", "rating": 5.0, "review": "(7)", "trip_type": "สถานที่ท่องเที่ยว", "image": "https://lh5.googleusercontent.com/p/AF1QipNOVWso8WbiwhHTtnXwt5L2JtpHmlk8mFK_FHDt=w122-h92-k-no"}}, {"model": "TourBuddy.trip", "pk": 118, "fields": {"location": "https://www.google.co.th/maps/place/%E0%B8%AD%E0%B8%B8%E0%B8%97%E0%B8%A2%E0%B8%B2%E0%B8%99%E0%B9%81%E0%B8%AB%E0%B9%88%E0%B8%87%E0%B8%8A%E0%B8%B2%E0%B8%95%E0%B8%B4%E0%B9%81%E0%B8%81%E0%B9%88%E0%B8%87%E0%B8%95%E0%B8%B0%E0%B8%99%E0%B8%B0/data=!4m7!3m6!1s0x3115b4431e81ff99:0xf587abe0b8b44762!8m2!3d15.2994899!4d105.4770746!16s%2Fm%2F0h7lng3!19sChIJmf-BHkO0FTERYke0uOCrh_U?authuser=0&hl=th&rclk=1", "latitude": 15.2994899, "longitude": 105.4770746, "name": "อุทยานแห่งชาติแก่งตะนะ", "rating": 4.3, "review": "(841)", "trip_type": "สถานที่ท่องเที่ยว", "image": "https://lh5.googleusercontent.com/p/AF1QipMxz1542Y9ZVabpcwUtOKACuaC4X5rUdOZZtFoG=w122-h92-k-no"}}, {"model": "TourBuddy.trip", "pk": 119, "fields": {"location": "https://www.google.co.th/maps/place/%E0%B8%9C%E0%B8%B2%E0%B8%8A%E0%B8%B0%E0%B8%99%E0%B8%B0%E0%B9%84%E0%B8%94/data=!4m7!3m6!1s0x31159838a3d50d97:0x49d6d8df167d1ce5!8m2!3d15.6208234!4d105.6173678!16s%2Fg%2F1hdzyp1dv!19sChIJlw3VoziYFTER5Rx9Ft_Y1kk?authuser=0&hl=th&rclk=1", "latitude": 15.6208234, "longitude": 105.6173678, "name": "ผาชะนะได", "rating": 4.7, "review": "(334)", "trip_type": "สถานที่ท่องเที่ยว", "image": "https://lh5.googleusercontent.com/p/AF1QipPqXnFT4NPpQcC7Uxw1eetS6DJHj-xdLMbSVYY=w122-h92-k-no"}}, {"model": "TourBuddy.trip", "pk": 120, "fields": {"location": "https://www.google.co.th/maps/place/%E0%B8%99%E0%B9%89%E0%B8%B3%E0%B8%95%E0%B8%81%E0%B8%AB%E0%B9%89%E0%B8%A7%E0%B8%A2%E0%B8%97%E0%B8%A3%E0%B8%B2%E0%B8%A2%E0%B9%83%E0%B8%AB%E0%B8%8D%E0%B9%88/data=!4m7!3m6!1s0x311444e583073339:0x2a8cc971dcc6a17b!8m2!3d14.9186492!4d105.5059244!16s%2Fg%2F1hdy_w_b7!19sChIJOTMHg-VEFDERe6HG3HHJjCo?authuser=0&hl=th&rclk=1", "latitude": 14.9186492, "longitude": 105.5059244, "name": "น้ำตกห้วยทรายใหญ่", "rating": 4.5, "review": "(15)", "trip_type": "สถานที่ท่องเที่ยว", "image": "https://lh5.googleusercontent.com/p/AF1QipNySPomfAz96ai-zA_2LamECjEKb0-h0bA-Oj1L=w80-h142-k-no"}}, {"model": "TourBuddy.trip", "pk": 121, "fields": {"location": "https://www.google.co.th/maps/place/%E0%B9%81%E0%B8%81%E0%B9%88%E0%B8%87%E0%B8%A5%E0%B8%B3%E0%B8%94%E0%B8%A7%E0%B8%99/data=!4m7!3m6!1s0x3114317d31476a1f:0x23c71e0ba2c752bf!8m2!3d15.1578792!4d105.2775454!16s%2Fg%2F11bzs1kqlx!19sChIJH2pHMX0xFDERv1LHogsexyM?authuser=0&hl=th&rclk=1", "latitude": 15.1578792, "longitude": 105.2775454, "name": "แก่งลำดวน", "rating": 3.9, "review": "(40)", "trip_type": "สถานที่ท่องเที่ยว", "image": "https://lh5.googleusercontent.com/p/AF1QipMa8cNX2doXROreI6L91GqN4kn2tjnDXJZbnGRG=w80-h142-k-no"}}, {"model": "TourBuddy.trip", "pk": 122, "fields": {"location": "https://www.google.co.th/maps/place/%E0%B8%A0%E0%B8%B9%E0%B8%AB%E0%B8%B4%E0%B8%99%E0%B8%94%E0%B9%88%E0%B8%B2%E0%B8%87/data=!4m7!3m6!1s0x31140ca9d71f05b3:0x91efc93e9bce7860!8m2!3d14.4714583!4d105.4688787!16s%2Fg%2F1hm69x9bc!19sChIJswUf16kMFDERYHjOmz7J75E?authuser=0&hl=th&rclk=1", "latitude": 14.4714583, "longitude": 105.4688787, "name": "ภูหินด่าง", "rating": 4.5, "review": "(15)", "trip_type": "สถานที่ท่องเที่ยว", "image": "https://lh5.googleusercontent.com/p/AF1QipNSjbPBuDvEHgX8IMx--XwGp_-AcR_rGgOJVi97=w138-h92-k-no"}}, {"model": "TourBuddy.trip", "pk": 123, "fields": {"location": "https://www.google.co.th/maps/place/%E0%B8%A7%E0%B8%B1%E0%B8%94%E0%B8%96%E0%B9%89%E0%B8%B3%E0%B9%80%E0%B8%AB%E0%B8%A7%E0%B8%AA%E0%B8%B4%E0%B8%99%E0%B8%98%E0%B8%B8%E0%B9%8C%E0%B8%8A%E0%B8%B1%E0%B8%A2/data=!4m7!3m6!1s0x3115b413d98fc205:0x801b9964f65a5083!8m2!3d15.3084445!4d105.4853834!16s%2Fg%2F1228rwg1!19sChIJBcKP2RO0FTERg1Ba9mSZG4A?authuser=0&hl=th&rclk=1", "latitude": 15.3084445, "longitude": 105.4853834, "name": "วัดถ้ำเหวสินธุ์ชัย", "rating": 4.4, "review": "(173)", "trip_type": "สถานที่ท่องเที่ยว", "image": "https://lh5.googleusercontent.com/p/AF1QipMb7Tr-3w-rJ565oBpYWMH10xvUG69gHPAgqR59=w138-h92-k-no"}}, {"model": "TourBuddy.trip", "pk": 124, "fields": {"location": "https://www.google.co.th/maps/place/%E0%B9%82%E0%B8%9A%E0%B8%A3%E0%B8%B2%E0%B8%93%E0%B8%AA%E0%B8%96%E0%B8%B2%E0%B8%99%E0%B9%82%E0%B8%99%E0%B8%99%E0%B9%81%E0%B8%81/data=!4m7!3m6!1s0x31169accd218ebb7:0x64f42eacecbde11d!8m2!3d15.0955228!4d104.8769247!16s%2Fg%2F11f2wq4g29!19sChIJt-sY0syaFjERHeG97Kwu9GQ?authuser=0&hl=th&rclk=1", "latitude": 15.0955228, "longitude": 104.8769247, "name": "โบราณสถานโนนแก", "rating": 4.3, "review": "(16)", "trip_type": "สถานที่ท่องเที่ยว", "image": "https://lh5.googleusercontent.com/p/AF1QipPM6Zn8a8yS8UYWqACDQceSGLX8lsbSwiAzM8cV=w122-h92-k-no"}}, {"model": "TourBuddy.trip", "pk": 125, "fields": {"location": "https://www.google.co.th/maps/place/Ubon+Street+Art+-+Happiness+%28%E0%B8%84%E0%B8%A7%E0%B8%B2%E0%B8%A1%E0%B8%AA%E0%B8%B8%E0%B8%82%29/data=!4m7!3m6!1s0x3116870414162aff:0xc1f9d63cf78b5a80!8m2!3d15.2251567!4d104.8596354!16s%2Fg%2F11jztzgtr2!19sChIJ_yoWFASHFjERgFqL9zzW-cE?authuser=0&hl=th&rclk=1", "latitude": 15.2251567, "longitude": 104.8596354, "name": "Ubon Street Art - Happiness (ความสุข)", "rating": 5.0, "review": "(2)", "trip_type": "สถานที่ท่องเที่ยว", "image": "https://lh5.googleusercontent.com/p/AF1QipPk1_Hoovy2_u4NLdSeMNn0-3knzIyRFdUX4aC0=w80-h106-k-no"}}, {"model": "TourBuddy.trip", "pk": 126, "fields": {"location": "https://www.google.co.th/maps/place/%E0%B8%AA%E0%B8%A7%E0%B8%99%E0%B9%80%E0%B8%AA%E0%B8%B7%E0%B8%AD%E0%B8%95%E0%B8%A3%E0%B8%B0%E0%B8%81%E0%B8%B2%E0%B8%A3/data=!4m7!3m6!1s0x311675bd88c8098f:0x38dcdfb9ae84c42!8m2!3d15.5735286!4d105.0086689!16s%2Fg%2F1td5j49x!19sChIJjwnIiL11FjERQkzomvvNjQM?authuser=0&hl=th&rclk=1", "latitude": 15.5735286, "longitude": 105.0086689, "name": "สวนเสือตระการ", "rating": 3.9, "review": "(189)", "trip_type": "สถานที่ท่องเที่ยว", "image": "https://lh5.googleusercontent.com/p/AF1QipNLzKkMU3-ebLthwUTTQ17MfljsMQZd-ubQ1WNy=w122-h92-k-no"}}, {"model": "TourBuddy.trip", "pk": 127, "fields": {"location": "https://www.google.co.th/maps/place/%E0%B8%AD%E0%B8%B8%E0%B8%97%E0%B8%A2%E0%B8%B2%E0%B8%99%E0%B9%81%E0%B8%AB%E0%B9%88%E0%B8%87%E0%B8%8A%E0%B8%B2%E0%B8%95%E0%B8%B4%E0%B8%9C%E0%B8%B2%E0%B9%81%E0%B8%95%E0%B9%89%E0%B8%A1/data=!4m7!3m6!1s0x3115a33294351715:0xcd2bb33dcf86f557!8m2!3d15.3987457!4d105.5075256!16s%2Fm%2F05f8t8k!19sChIJFRc1lDKjFTERV_WGzz2zK80?authuser=0&hl=th&rclk=1", "latitude": 15.3987457, "longitude": 105.5075256, "name": "อุทยานแห่งชาติผาแต้ม", "rating": 4.5, "review": "(2,946)", "trip_type": "อุทยานแห่งชาติ", "image": "https://lh5.googleusercontent.com/p/AF1QipPP-gYIt0ijYwXgan-ueBY9D-UEcGSpMawQu06E=w137-h92-k-no"}}, {"model": "TourBuddy.trip", "pk": 128, "fields": {"location": "https://www.google.co.th/maps/place/%E0%B8%97%E0%B8%B8%E0%B9%88%E0%B8%87%E0%B8%94%E0%B8%AD%E0%B8%81%E0%B8%AA%E0%B8%A3%E0%B9%89%E0%B8%AD%E0%B8%A2%E0%B8%AA%E0%B8%B8%E0%B8%A7%E0%B8%A3%E0%B8%A3%E0%B8%93%E0%B8%B2%28%E0%B8%81%E0%B8%A3%E0%B8%B0%E0%B8%94%E0%B8%B8%E0%B8%A1%E0%B9%80%E0%B8%87%E0%B8%B4%E0%B8%99,%E0%B8%81%E0%B8%A3%E0%B8%B0%E0%B8%94%E0%B8%B8%E0%B8%A1%E0%B8%97%E0%B8%AD%E0%B8%87%29/data=!4m7!3m6!1s0x311685b31e9e62eb:0xcde1e0c1b2cc3403!8m2!3d15.1631847!4d104.9380029!16s%2Fg%2F11fhjmt5hg!19sChIJ62KeHrOFFjERAzTMssHg4c0?authuser=0&hl=th&rclk=1", "latitude": 15.1631847, "longitude": 104.9380029, "name": "ทุ่งดอกสร้อยสุวรรณา(กระดุมเงิน,กระดุมทอง)", "rating": 4.5, "review": "(32)", "trip_type": "สถานที่ท่องเที่ยว", "image": "https://lh5.googleusercontent.com/p/AF1QipMpEmYLRh9mCgBI1-oHX5u3e4NApZwGfKQx7los=w122-h92-k-no"}}, {"model": "TourBuddy.trip", "pk": 129, "fields": {"location": "https://www.google.co.th/maps/place/%E0%B8%A7%E0%B8%B1%E0%B8%94%E0%B8%A8%E0%B8%A3%E0%B8%B5%E0%B8%AD%E0%B8%B8%E0%B8%9A%E0%B8%A5%E0%B8%A3%E0%B8%B1%E0%B8%95%E0%B8%99%E0%B8%B2%E0%B8%A3%E0%B8%B2%E0%B8%A1+%28%E0%B8%A7%E0%B8%B1%E0%B8%94%E0%B8%A8%E0%B8%A3%E0%B8%B5%E0%B8%97%E0%B8%AD%E0%B8%87%29/data=!4m7!3m6!1s0x311686322282a127:0x38d026a6e2bc7ed1!8m2!3d15.227493!4d104.8562582!16s%2Fg%2F121ln4yp!19sChIJJ6GCIjKGFjER0X684qYm0Dg?authuser=0&hl=th&rclk=1", "latitude": 15.227493, "longitude": 104.8562582, "name": "วัดศรีอุบลรัตนาราม (วัดศรีทอง)", "rating": 4.5, "review": "(280)", "trip_type": "สถานที่ท่องเที่ยว", "image": "https://lh5.googleusercontent.com/p/AF1QipM9jqaNnW05rZtZZGdJEoj7iAfPeq6iVsyD2DtK=w137-h92-k-no"}}, {"model": "TourBuddy.trip", "pk": 130, "fields": {"location": "https://www.google.co.th/maps/place/%E0%B8%9A%E0%B9%89%E0%B8%B2%E0%B8%99%E0%B8%AA%E0%B8%A7%E0%B8%99%E0%B8%9B%E0%B8%B1%E0%B8%99%E0%B8%AA%E0%B8%B8%E0%B8%82%26%E0%B9%81%E0%B8%A5%E0%B8%8A%E0%B8%B2%E0%B8%A2%E0%B8%99%E0%B9%8C%E0%B8%9B%E0%B8%A5%E0%B8%B2%E0%B8%A2%E0%B8%99%E0%B8%B2%E0%B8%84%E0%B8%B2%E0%B9%80%E0%B8%9F%E0%B9%88/data=!4m7!3m6!1s0x31168f1cf4dec29f:0x4640b3baaacab9d2!8m2!3d15.166748!4d104.830124!16s%2Fg%2F11trcfdrpq!19sChIJn8Le9ByPFjER0rnKqrqzQEY?authuser=0&hl=th&rclk=1", "latitude": 15.166748, "longitude": 104.830124, "name": "บ้านสวนปันสุข&แลชายน์ปลายนาคาเฟ่", "rating": null, "review": "", "trip_type": "สถานที่ท่องเที่ยว", "image": "https://maps.gstatic.com/tactile/pane/result-no-thumbnail-2x.png"}}, {"model": "TourBuddy.trip", "pk": 131, "fields": {"location": "https://www.google.co.th/maps/place/%E0%B8%AD%E0%B8%B8%E0%B8%97%E0%B8%A2%E0%B8%B2%E0%B8%99%E0%B9%81%E0%B8%AB%E0%B9%88%E0%B8%87%E0%B8%8A%E0%B8%B2%E0%B8%95%E0%B8%B4%E0%B8%A0%E0%B8%B9%E0%B8%88%E0%B8%AD%E0%B8%87%E0%B8%99%E0%B8%B2%E0%B8%A2%E0%B8%AD%E0%B8%A2/data=!4m7!3m6!1s0x3113f15b1b67d523:0xad04750506af6533!8m2!3d14.4343231!4d105.2521579!16s%2Fm%2F0h7q5zs!19sChIJI9VnG1vxEzERM2WvBgV1BK0?authuser=0&hl=th&rclk=1", "latitude": 14.4343231, "longitude": 105.2521579, "name": "อุทยานแห่งชาติภูจองนายอย", "rating": 4.5, "review": "(526)", "trip_type": "สถานที่ท่องเที่ยว", "image": "https://lh5.googleusercontent.com/p/AF1QipPeUxIVHUjCbgyc-Xp7V-fOWejtzHJL_s1nWSXT=w80-h120-k-no"}}, {"model": "TourBuddy.trip", "pk": 132, "fields": {"location": "https://www.google.co.th/maps/place/%E0%B8%97%E0%B9%88%E0%B8%AD%E0%B8%87%E0%B9%80%E0%B8%97%E0%B8%B5%E0%B9%88%E0%B8%A2%E0%B8%A7%E0%B9%80%E0%B8%8A%E0%B8%B4%E0%B8%87%E0%B9%80%E0%B8%81%E0%B8%A9%E0%B8%95%E0%B8%A3%E0%B8%AD%E0%B8%B8%E0%B8%9A%E0%B8%A5%E0%B8%A3%E0%B8%B2%E0%B8%8A%E0%B8%98%E0%B8%B2%E0%B8%99%E0%B8%B5/data=!4m7!3m6!1s0x311681c120f04f79:0xaf1af189792d83ef!8m2!3d15.2388842!4d105.0067442!16s%2Fg%2F11sx0mgt2y!19sChIJeU_wIMGBFjER74MteYnxGq8?authuser=0&hl=th&rclk=1", "latitude": 15.2388842, "longitude": 105.0067442, "name": "ท่องเที่ยวเชิงเกษตรอุบลราชธานี", "rating": null, "review": "", "trip_type": "สถานที่ท่องเที่ยว", "image": "https://streetviewpixels-pa.googleapis.com/v1/thumbnail?panoid=nC8b6C8LpmaUAYgB_9IVtw&cb_client=search.gws-prod.gps&w=80&h=92&yaw=121.7087&pitch=0&thumbfov=100"}}, {"model": "TourBuddy.trip", "pk": 133, "fields": {"location": "https://www.google.co.th/maps/place/%E0%B8%AB%E0%B8%B2%E0%B8%94%E0%B8%97%E0%B9%88%E0%B8%B2%E0%B9%82%E0%B8%AE%E0%B8%87+%E0%B8%88%E0%B8%B8%E0%B8%94%E0%B8%9A%E0%B8%A3%E0%B8%A3%E0%B8%88%E0%B8%9A%E0%B9%81%E0%B8%A1%E0%B9%88%E0%B8%99%E0%B9%89%E0%B8%B3%E0%B8%8A%E0%B8%B5-%E0%B8%A1%E0%B8%B9%E0%B8%A5/data=!4m7!3m6!1s0x31168c642fdea631:0x41cd2e77ea951849!8m2!3d15.1814823!4d104.713561!16s%2Fg%2F11g03jwgkq!19sChIJMabeL2SMFjERSRiV6ncuzUE?authuser=0&hl=th&rclk=1", "latitude": 15.1814823, "longitude": 104.713561, "name": "หาดท่าโฮง จุดบรรจบแม่น้ำชี-มูล", "rating": 4.5, "review": "(21)", "trip_type": "สถานที่ท่องเที่ยว", "image": "https://lh5.googleusercontent.com/p/AF1QipPgF6MUhn5M_vuwnZ5gqkzBXeFfIQTlIxtN_Yox=w138-h92-k-no"}}, {"model": "TourBuddy.trip", "pk": 134, "fields": {"location": "https://www.google.co.th/maps/place/%E0%B8%9B%E0%B9%89%E0%B8%B2%E0%B8%A2%E0%B8%A2%E0%B8%B4%E0%B8%99%E0%B8%94%E0%B8%B5%E0%B8%95%E0%B9%89%E0%B8%AD%E0%B8%99%E0%B8%A3%E0%B8%B1%E0%B8%9A%E0%B8%AA%E0%B8%B9%E0%B9%88+%E0%B8%88%E0%B8%B1%E0%B8%87%E0%B8%AB%E0%B8%A7%E0%B8%B1%E0%B8%94%E0%B8%AD%E0%B8%B8%E0%B8%9A%E0%B8%A5%E0%B8%A3%E0%B8%B2%E0%B8%8A%E0%B8%98%E0%B8%B2%E0%B8%99%E0%B8%B5/data=!4m7!3m6!1s0x3116896ff917a9fd:0x6f2be3727bd0f1c0!8m2!3d15.2656861!4d104.821775!16s%2Fg%2F11fsnvgjzg!19sChIJ_akX-W-JFjERwPHQe3LjK28?authuser=0&hl=th&rclk=1", "latitude": 15.2656861, "longitude": 104.821775, "name": "ป้ายยินดีต้อนรับสู่ จังหวัดอุบลราชธานี", "rating": 5.0, "review": "(1)", "trip_type": "สถานที่ท่องเที่ยว", "image": "https://streetviewpixels-pa.googleapis.com/v1/thumbnail?panoid=rGPILIr3aypzMthwdK_gcQ&cb_client=search.gws-prod.gps&w=80&h=92&yaw=244.77875&pitch=0&thumbfov=100"}}, {"model": "TourBuddy.trip", "pk": 135, "fields": {"location": "https://www.google.co.th/maps/place/%E0%B8%AB%E0%B8%AD%E0%B9%84%E0%B8%95%E0%B8%A3%E0%B8%81%E0%B8%A5%E0%B8%B2%E0%B8%87%E0%B8%99%E0%B9%89%E0%B8%B3/data=!4m7!3m6!1s0x31168775d9d6c8c5:0x14ce55e53c6387cb!8m2!3d15.2299353!4d104.8612333!16s%2Fg%2F11gtfrmwt9!19sChIJxcjW2XWHFjERy4djPOVVzhQ?authuser=0&hl=th&rclk=1", "latitude": 15.2299353, "longitude": 104.8612333, "name": "หอไตรกลางน้ำ", "rating": 4.7, "review": "(7)", "trip_type": "วัด", "image": "https://lh5.googleusercontent.com/p/AF1QipP6KURkMQRrPma0nQZiKwO16S29F0UUCIxaK1rd=w122-h92-k-no"}}, {"model": "TourBuddy.trip", "pk": 136, "fields": {"location": "https://www.google.co.th/maps/place/%E0%B8%AA%E0%B8%A7%E0%B8%99%E0%B8%AA%E0%B8%B1%E0%B8%95%E0%B8%A7%E0%B9%8C%E0%B8%AD%E0%B8%B8%E0%B8%9A%E0%B8%A5%E0%B8%A3%E0%B8%B2%E0%B8%8A%E0%B8%98%E0%B8%B2%E0%B8%99%E0%B8%B5/data=!4m7!3m6!1s0x3116635b1a320bfb:0x6e31ed1b257ddb68!8m2!3d15.2839683!4d104.8078531!16s%2Fg%2F11b6ybc8nx!19sChIJ-wsyGltjFjERaNt9JRvtMW4?authuser=0&hl=th&rclk=1", "latitude": 15.2839683, "longitude": 104.8078531, "name": "สวนสัตว์อุบลราชธานี", "rating": 4.3, "review": "(1,746)", "trip_type": "สถานที่ท่องเที่ยว", "image": "https://lh5.googleusercontent.com/p/AF1QipM4MR11FFePOcVZoltxrgqppPuR0Y3vyEyClBWq=w122-h92-k-no"}}, {"model": "TourBuddy.trip", "pk": 137, "fields": {"location": "https://www.google.co.th/maps/place/%E0%B8%AB%E0%B8%B2%E0%B8%94%E0%B8%AD%E0%B9%87%E0%B8%AD%E0%B8%94%E0%B8%AD%E0%B9%87%E0%B8%AD%E0%B8%94/data=!4m7!3m6!1s0x31168d3cd905fb0b:0xc105fc644973d406!8m2!3d15.1885174!4d104.6993444!16s%2Fg%2F11sjvvcpyr!19sChIJC_sF2TyNFjERBtRzSWT8BcE?authuser=0&hl=th&rclk=1", "latitude": 15.1885174, "longitude": 104.6993444, "name": "หาดอ็อดอ็อด", "rating": null, "review": "", "trip_type": "สถานที่ท่องเที่ยว", "image": "https://lh5.googleusercontent.com/p/AF1QipPGW0oQSuISGSv4JV3xYA4jVp58r9xULWlkZ_Va=w122-h92-k-no"}}, {"model": "TourBuddy.trip", "pk": 138, "fields": {"location": "https://www.google.co.th/maps/place/%E0%B8%A8%E0%B8%B9%E0%B8%99%E0%B8%A2%E0%B9%8C%E0%B9%80%E0%B8%A3%E0%B8%B5%E0%B8%A2%E0%B8%99%E0%B8%A3%E0%B8%B9%E0%B9%89%E0%B8%A1%E0%B8%B5%E0%B8%8A%E0%B8%B5%E0%B8%A7%E0%B8%B2/data=!4m7!3m6!1s0x311681b1889f079b:0xabddbcf7126d6a82!8m2!3d15.2358201!4d104.9973028!16s%2Fg%2F11sjbzgzty!19sChIJmwefiLGBFjERgmptEve83as?authuser=0&hl=th&rclk=1", "latitude": 15.2358201, "longitude": 104.9973028, "name": "ศูนย์เรียนรู้มีชีวา", "rating": null, "review": "", "trip_type": "สถานที่ท่องเที่ยว", "image": "https://maps.gstatic.com/tactile/pane/result-no-thumbnail-2x.png"}}, {"model": "TourBuddy.trip", "pk": 139, "fields": {"location": "https://www.google.co.th/maps/place/%E0%B8%A7%E0%B8%B1%E0%B8%94%E0%B9%81%E0%B8%88%E0%B9%89%E0%B8%87/data=!4m7!3m6!1s0x311687cdacf2088f:0x94719e118d0f2dac!8m2!3d15.2366083!4d104.8601155!16s%2Fg%2F11bx82h7wq!19sChIJjwjyrM2HFjERrC0PjRGecZQ?authuser=0&hl=th&rclk=1", "latitude": 15.2366083, "longitude": 104.8601155, "name": "วัดแจ้ง", "rating": 4.3, "review": "(382)", "trip_type": "สถานที่ท่องเที่ยว", "image": "https://lh5.googleusercontent.com/p/AF1QipOBcLokBdgWPqK8mGSg7CCihNpaVJoJkQffTC8=w80-h142-k-no"}}, {"model": "TourBuddy.trip", "pk": 140, "fields": {"location": "https://www.google.co.th/maps/place/%E0%B8%AE%E0%B8%B1%E0%B8%81%E0%B8%99%E0%B8%B0@%E0%B8%97%E0%B8%B8%E0%B9%88%E0%B8%87%E0%B8%99%E0%B8%B2%E0%B8%84%E0%B8%B3+%E0%B8%84%E0%B8%B2%E0%B9%80%E0%B8%9F%E0%B9%88%E0%B9%81%E0%B8%AD%E0%B8%99%E0%B8%94%E0%B9%8C%E0%B8%9F%E0%B8%B2%E0%B8%A3%E0%B9%8C%E0%B8%A1/data=!4m7!3m6!1s0x311685425772b2c3:0x7ac59947cef8ee60!8m2!3d15.152396!4d104.9035014!16s%2Fg%2F11ff27t3g9!19sChIJw7JyV0KFFjERYO74zkeZxXo?authuser=0&hl=th&rclk=1", "latitude": 15.152396, "longitude": 104.9035014, "name": "ฮักนะ@ทุ่งนาคำ คาเฟ่แอนด์ฟาร์ม", "rating": 4.4, "review": "(28)", "trip_type": "สถานที่ท่องเที่ยว", "image": "https://lh5.googleusercontent.com/p/AF1QipMqDzhSM9_sIlbi9ZkGau7T-et9ntLJlqwESHcM=w122-h92-k-no"}}, {"model": "TourBuddy.trip", "pk": 141, "fields": {"location": "https://www.google.co.th/maps/place/%E0%B8%AD%E0%B8%9A%E0%B8%AA%E0%B8%A1%E0%B8%B8%E0%B8%99%E0%B9%84%E0%B8%9E%E0%B8%A3%E0%B8%A7%E0%B8%B1%E0%B8%94%E0%B8%AB%E0%B8%99%E0%B8%AD%E0%B8%87%E0%B8%9B%E0%B8%A5%E0%B8%B2%E0%B8%9B%E0%B8%B2%E0%B8%81/data=!4m7!3m6!1s0x31166313a1d94a19:0x82fe6f218217fc8!8m2!3d15.2829144!4d104.8295253!16s%2Fg%2F11v0qtctk7!19sChIJGUrZoRNjFjERyH8hGPLmLwg?authuser=0&hl=th&rclk=1", "latitude": 15.2829144, "longitude": 104.8295253, "name": "อบสมุนไพรวัดหนองปลาปาก", "rating": null, "review": "", "trip_type": "สถานที่ท่องเที่ยว", "image": "https://lh5.googleusercontent.com/p/AF1QipPAPN_zHacAXxUZOiaKAAgP8GE_cC-jjKe4s13J=w80-h142-k-no"}}, {"model": "TourBuddy.trip", "pk": 142, "fields": {"location": "https://www.google.co.th/maps/place/%E0%B8%AA%E0%B8%B0%E0%B8%9E%E0%B8%B2%E0%B8%99%E0%B9%84%E0%B8%A1%E0%B9%89%E0%B8%AD%E0%B8%A1%E0%B8%95%E0%B8%B0/data=!4m7!3m6!1s0x3116634a5cf5718d:0x23b187217126a7ee!8m2!3d15.3267018!4d104.7818825!16s%2Fg%2F11nn01p294!19sChIJjXH1XEpjFjER7qcmcSGHsSM?authuser=0&hl=th&rclk=1", "latitude": 15.3267018, "longitude": 104.7818825, "name": "สะพานไม้อมตะ", "rating": 5.0, "review": "(1)", "trip_type": "สถานที่ท่องเที่ยว", "image": "https://lh5.googleusercontent.com/p/AF1QipMRxKNERhZkMBnWBSgJ6SXj9THFXdOjo7WL1rM9=w103-h92-k-no"}}, {"model": "TourBuddy.trip", "pk": 143, "fields": {"location": "https://www.google.co.th/maps/place/%E0%B8%99%E0%B8%B2%E0%B8%AB%E0%B8%99%E0%B8%AD%E0%B8%87%E0%B9%81%E0%B8%84%E0%B8%99%E0%B9%81%E0%B8%94%E0%B8%99%E0%B8%AB%E0%B8%AD%E0%B8%A2%E0%B8%88%E0%B8%B5%E0%B9%88/data=!4m7!3m6!1s0x31167f7fcd295c1b:0x193ded79783ea482!8m2!3d15.3045139!4d105.0295487!16s%2Fg%2F11trhx7lb2!19sChIJG1wpzX9_FjERgqQ-eHntPRk?authuser=0&hl=th&rclk=1", "latitude": 15.3045139, "longitude": 105.0295487, "name": "นาหนองแคนแดนหอยจี่", "rating": null, "review": "", "trip_type": "สถานที่ท่องเที่ยว", "image": "https://maps.gstatic.com/tactile/pane/result-no-thumbnail-2x.png"}}, {"model": "TourBuddy.trip", "pk": 144, "fields": {"location": "https://www.google.co.th/maps/place/%E0%B8%97%E0%B8%B8%E0%B9%88%E0%B8%87%E0%B8%99%E0%B8%B2%E0%B8%9A%E0%B8%B1%E0%B8%A7%E0%B8%AB%E0%B9%88%E0%B8%AD%E0%B8%87%E0%B9%81%E0%B8%94%E0%B8%87/data=!4m7!3m6!1s0x3115d7a8694ffe0d:0xd8b14c7f0ac1b3aa!8m2!3d15.3783547!4d105.0995227!16s%2Fg%2F11fd4k2hfw!19sChIJDf5PaajXFTERqrPBCn9Msdg?authuser=0&hl=th&rclk=1", "latitude": 15.3783547, "longitude": 105.0995227, "name": "ทุ่งนาบัวห่องแดง", "rating": 4.1, "review": "(40)", "trip_type": "สถานที่ท่องเที่ยว", "image": "https://lh5.googleusercontent.com/p/AF1QipOc17Ze7MPtz0OQujY_v6YkA6oaYBQWPXMrzuSE=w122-h92-k-no"}}, {"model": "TourBuddy.trip", "pk": 145, "fields": {"location": "https://www.google.co.th/maps/place/%E0%B8%98%E0%B8%A7%E0%B8%B1%E0%B8%8A%E0%B8%8A%E0%B8%B1%E0%B8%A2%E0%B9%81%E0%B8%AD%E0%B8%99%E0%B8%94%E0%B9%8C%E0%B9%81%E0%B8%9E%E0%B8%A5%E0%B8%99%E0%B8%95%E0%B8%B4%E0%B8%8A/data=!4m7!3m6!1s0x31167da739223ddd:0x9c33287232e4b297!8m2!3d15.2765788!4d104.921222!16s%2Fg%2F11snylzpz3!19sChIJ3T0iOad9FjERl7LkMnIoM5w?authuser=0&hl=th&rclk=1", "latitude": 15.2765788, "longitude": 104.921222, "name": "ธวัชชัยแอนด์แพลนติช", "rating": 5.0, "review": "(1)", "trip_type": "สถานที่ท่องเที่ยว", "image": "https://lh5.googleusercontent.com/p/AF1QipMtFB7MGTPZQgUo2JxAIqrAP57Hiu4k2Pakdbqd=w122-h92-k-no"}}, {"model": "TourBuddy.trip", "pk": 146, "fields": {"location": "https://www.google.co.th/maps/place/%E0%B8%9C%E0%B8%B2%E0%B8%A7%E0%B8%B1%E0%B8%94%E0%B9%83%E0%B8%88/data=!4m7!3m6!1s0x31144afa9fba3d6d:0xdb391c372499a504!8m2!3d15.2036173!4d105.4420724!16s%2Fg%2F11hbv9y3dd!19sChIJbT26n_pKFDERBKWZJDccOds?authuser=0&hl=th&rclk=1", "latitude": 15.2036173, "longitude": 105.4420724, "name": "ผาวัดใจ", "rating": 4.6, "review": "(66)", "trip_type": "สถานที่ท่องเที่ยว", "image": "https://lh5.googleusercontent.com/p/AF1QipN7PeQiqOYyynmXM4ZKdpIzCmYiGKXNQSVTSQRX=w80-h164-k-no"}}, {"model": "TourBuddy.trip", "pk": 147, "fields": {"location": "https://www.google.co.th/maps/place/%E0%B8%9A%E0%B9%89%E0%B8%B2%E0%B8%99%E0%B8%AA%E0%B8%A7%E0%B8%99%E0%B8%9B%E0%B8%A3%E0%B8%B0%E0%B8%AA%E0%B8%B2%E0%B8%A3%E0%B8%9E%E0%B8%A3/data=!4m7!3m6!1s0x3115d3fe14d80573:0xf2fa9e3f06a6eac!8m2!3d15.3406785!4d105.1302165!16s%2Fg%2F11sdvdnc5f!19sChIJcwXYFP7TFTERrG5q8OOpLw8?authuser=0&hl=th&rclk=1", "latitude": 15.3406785, "longitude": 105.1302165, "name": "บ้านสวนประสารพร", "rating": null, "review": "", "trip_type": "สถานที่ท่องเที่ยว", "image": "https://lh5.googleusercontent.com/p/AF1QipMSzOC2DuZ_utra812tjLju-Mz5uUbfowhJBu_S=w122-h92-k-no"}}, {"model": "TourBuddy.trip", "pk": 148, "fields": {"location": "https://www.google.co.th/maps/place/%E0%B8%99%E0%B9%89%E0%B8%B3%E0%B8%95%E0%B8%81%E0%B8%95%E0%B8%B2%E0%B8%94%E0%B9%82%E0%B8%95%E0%B8%99/data=!4m7!3m6!1s0x3115b4b938d0cca7:0xfcbdc87ba0054882!8m2!3d15.253229!4d105.478071!16s%2Fg%2F1tfn05mv!19sChIJp8zQOLm0FTERgkgFoHvIvfw?authuser=0&hl=th&rclk=1", "latitude": 15.253229, "longitude": 105.478071, "name": "น้ำตกตาดโตน", "rating": 4.2, "review": "(101)", "trip_type": "สถานที่ท่องเที่ยว", "image": "https://lh5.googleusercontent.com/p/AF1QipPzkXKknEz8l8dN_u1gO1HfQjTMfKyxzTdKGnk=w122-h92-k-no"}}, {"model": "TourBuddy.trip", "pk": 149, "fields": {"location": "https://www.google.co.th/maps/place/%E0%B8%AA%E0%B8%A7%E0%B8%99%E0%B9%84%E0%B8%A1%E0%B9%89%E0%B8%AA%E0%B8%B1%E0%B8%81+%E0%B8%A3%E0%B9%89%E0%B8%AD%E0%B8%A2+%E0%B8%A5%E0%B9%89%E0%B8%B2%E0%B8%99/data=!4m7!3m6!1s0x311681298ebcb6b3:0xfe24ded56ea25c55!8m2!3d15.1873742!4d105.0071861!16s%2Fg%2F11j8w223kk!19sChIJs7a8jimBFjERVVyibtXeJP4?authuser=0&hl=th&rclk=1", "latitude": 15.1873742, "longitude": 105.0071861, "name": "สวนไม้สัก ร้อย ล้าน", "rating": 5.0, "review": "(1)", "trip_type": "สถานที่ท่องเที่ยว", "image": "https://streetviewpixels-pa.googleapis.com/v1/thumbnail?panoid=wD9b4phtp5lJYWZ-vyqaMA&cb_client=search.gws-prod.gps&w=80&h=92&yaw=148.2193&pitch=0&thumbfov=100"}}, {"model": "TourBuddy.trip", "pk": 150, "fields": {"location": "https://www.google.co.th/maps/place/%E0%B8%AA%E0%B8%B3%E0%B8%99%E0%B8%B1%E0%B8%81%E0%B8%87%E0%B8%B2%E0%B8%99%E0%B8%81%E0%B8%B2%E0%B8%A3%E0%B8%97%E0%B9%88%E0%B8%AD%E0%B8%87%E0%B9%80%E0%B8%97%E0%B8%B5%E0%B9%88%E0%B8%A2%E0%B8%A7%E0%B9%81%E0%B8%A5%E0%B8%B0%E0%B8%81%E0%B8%B5%E0%B8%AC%E0%B8%B2%E0%B8%88%E0%B8%B1%E0%B8%87%E0%B8%AB%E0%B8%A7%E0%B8%B1%E0%B8%94%E0%B8%AD%E0%B8%B8%E0%B8%9A%E0%B8%A5%E0%B8%A3%E0%B8%B2%E0%B8%8A%E0%B8%98%E0%B8%B2%E0%B8%99%E0%B8%B5/data=!4m7!3m6!1s0x31168688ea084453:0x13ae9202a0f13052!8m2!3d15.1985367!4d104.8961581!16s%2Fg%2F1pp2x5vbb!19sChIJU0QI6oiGFjERUjDxoAKSrhM?authuser=0&hl=th&rclk=1", "latitude": 15.1985367, "longitude": 104.8961581, "name": "สำนักงานการท่องเที่ยวและกีฬาจังหวัดอุบลราชธานี", "rating": 3.8, "review": "(5)", "trip_type": "สถานที่ราชการ", "image": "https://lh5.googleusercontent.com/p/AF1QipO0RgwV4MFa3WqWBpleZsgx5LChA9Nz2LBuRSnd=w164-h92-k-no"}}, {"model": "TourBuddy.trip", "pk": 151, "fields": {"location": "https://www.google.co.th/maps/place/%E0%B8%82%E0%B8%B1%E0%B8%A7%E0%B8%99%E0%B9%89%E0%B8%AD%E0%B8%A2%E0%B8%9A%E0%B9%89%E0%B8%B2%E0%B8%99%E0%B8%9A%E0%B8%B8%E0%B9%88%E0%B8%87%E0%B8%AB%E0%B8%A7%E0%B8%B2%E0%B8%A2/data=!4m7!3m6!1s0x31168fb86fe9bf99:0x8f407e786337d569!8m2!3d15.163254!4d104.760153!16s%2Fg%2F11hymbpsq7!19sChIJmb_pb7iPFjERadU3Y3h-QI8?authuser=0&hl=th&rclk=1", "latitude": 15.163254, "longitude": 104.760153, "name": "ขัวน้อยบ้านบุ่งหวาย", "rating": 4.0, "review": "(8)", "trip_type": "สถานที่ท่องเที่ยว", "image": "https://lh5.googleusercontent.com/p/AF1QipPsq6OzNsPED-bgeHZLlmyEeGkb6BNvXYxJdm4=w163-h92-k-no"}}, {"model": "TourBuddy.trip", "pk": 152, "fields": {"location": "https://www.google.co.th/maps/place/lc95shop/data=!4m7!3m6!1s0x3116637e84e5a279:0x2b7b605079300b20!8m2!3d15.3199999!4d104.7637619!16s%2Fg%2F11thl9h0zw!19sChIJeaLlhH5jFjERIAsweVBgeys?authuser=0&hl=th&rclk=1", "latitude": 15.3199999, "longitude": 104.7637619, "name": "lc95shop", "rating": null, "review": "", "trip_type": "สถานที่ท่องเที่ยว", "image": "https://maps.gstatic.com/tactile/pane/result-no-thumbnail-2x.png"}}, {"model": "TourBuddy.trip", "pk": 153, "fields": {"location": "https://www.google.co.th/maps/place/%E0%B8%AB%E0%B8%99%E0%B8%AD%E0%B8%87%E0%B8%8A%E0%B9%89%E0%B8%B2%E0%B8%87+%28%E0%B8%95.%E0%B8%AB%E0%B8%99%E0%B8%AD%E0%B8%87%E0%B8%82%E0%B8%AD%E0%B8%99%29/data=!4m7!3m6!1s0x3116615123d80e3d:0xb62a42537920155b!8m2!3d15.3221675!4d104.7132647!16s%2Fg%2F11f781rzzn!19sChIJPQ7YI1FhFjERWxUgeVNCKrY?authuser=0&hl=th&rclk=1", "latitude": 15.3221675, "longitude": 104.7132647, "name": "หนองช้าง (ต.หนองขอน)", "rating": 5.0, "review": "(2)", "trip_type": "สถานที่ท่องเที่ยว", "image": "https://maps.gstatic.com/tactile/pane/result-no-thumbnail-2x.png"}}, {"model": "TourBuddy.trip", "pk": 154, "fields": {"location": "https://www.google.co.th/maps/place/%E0%B8%A8%E0%B8%B2%E0%B8%A5%E0%B8%B2%E0%B8%A3%E0%B9%88%E0%B8%A7%E0%B8%A1%E0%B9%83%E0%B8%88%28SML%29+%E0%B8%8A%E0%B8%B8%E0%B8%A1%E0%B8%8A%E0%B8%99%E0%B8%A7%E0%B8%B1%E0%B8%94%E0%B8%A7%E0%B8%B2%E0%B8%A3%E0%B8%B4%E0%B8%99%E0%B8%97%E0%B8%A3%E0%B8%B2%E0%B8%A3%E0%B8%B2%E0%B8%A1/data=!4m7!3m6!1s0x31168712c779b64f:0x72a8871a4d04f5fc!8m2!3d15.2044078!4d104.8646793!16s%2Fg%2F11r4mvcqgd!19sChIJT7Z5xxKHFjER_PUETRqHqHI?authuser=0&hl=th&rclk=1", "latitude": 15.2044078, "longitude": 104.8646793, "name": "ศาลาร่วมใจ(SML) ชุมชนวัดวารินทราราม", "rating": null, "review": "", "trip_type": "สถานที่ท่องเที่ยว", "image": "https://streetviewpixels-pa.googleapis.com/v1/thumbnail?panoid=mk3D-4hCELboxAXfBETcUw&cb_client=search.gws-prod.gps&w=80&h=92&yaw=263.97928&pitch=0&thumbfov=100"}}, {"model": "TourBuddy.trip", "pk": 155, "fields": {"location": "https://www.google.co.th/maps/place/%E0%B8%AA%E0%B8%96%E0%B8%B2%E0%B8%99%E0%B8%B5%E0%B8%95%E0%B8%B3%E0%B8%A3%E0%B8%A7%E0%B8%88%E0%B8%97%E0%B9%88%E0%B8%AD%E0%B8%87%E0%B9%80%E0%B8%97%E0%B8%B5%E0%B9%88%E0%B8%A2%E0%B8%A7+3+%28%E0%B8%AD%E0%B8%B8%E0%B8%9A%E0%B8%A5%E0%B8%A3%E0%B8%B2%E0%B8%8A%E0%B8%98%E0%B8%B2%E0%B8%99%E0%B8%B5%29+%E0%B8%81%E0%B8%AD%E0%B8%87%E0%B8%81%E0%B8%B3%E0%B8%81%E0%B8%B1%E0%B8%9A%E0%B8%81%E0%B8%B2%E0%B8%A3+1+%E0%B8%81%E0%B8%AD%E0%B8%87%E0%B8%9A%E0%B8%B1%E0%B8%87%E0%B8%84%E0%B8%B1%E0%B8%9A%E0%B8%81%E0%B8%B2%E0%B8%A3%E0%B8%95%E0%B8%B3%E0%B8%A3%E0%B8%A7%E0%B8%88%E0%B8%97%E0%B9%88%E0%B8%AD%E0%B8%87%E0%B9%80%E0%B8%97%E0%B8%B5%E0%B9%88%E0%B8%A2%E0%B8%A7+2/data=!4m7!3m6!1s0x31168688c163f87b:0xe389f09b21df043c!8m2!3d15.1987503!4d104.8967407!16s%2Fg%2F11d_d4rzkh!19sChIJe_hjwYiGFjERPATfIZvwieM?authuser=0&hl=th&rclk=1", "latitude": 15.1987503, "longitude": 104.8967407, "name": "สถานีตำรวจท่องเที่ยว 3 (อุบลราชธานี) กองกำกับการ 1 กองบังคับการตำรวจท่องเที่ยว 2", "rating": 4.8, "review": "(5)", "trip_type": "สถานีตำรวจ", "image": "https://lh5.googleusercontent.com/p/AF1QipNYJT7Y4iuWtiOOm3tYpryOhx1-TGbfIfaL6tQ4=w80-h106-k-no"}}, {"model": "TourBuddy.trip", "pk": 156, "fields": {"location": "https://www.google.co.th/maps/place/%E0%B8%AA%E0%B8%A7%E0%B8%99%E0%B8%99%E0%B9%89%E0%B8%B3%E0%B8%AD%E0%B8%B8%E0%B8%9A%E0%B8%A5%E0%B8%97%E0%B8%AD%E0%B8%87%E0%B8%AB%E0%B8%A5%E0%B9%88%E0%B8%AD%E0%B8%A7%E0%B8%B4%E0%B8%AA%E0%B8%95%E0%B9%89%E0%B8%B2/data=!4m7!3m6!1s0x3116862dfb48b813:0x5685b5da3519937a!8m2!3d15.2872294!4d104.8429947!16s%2Fg%2F11b7h3w_gy!19sChIJE7hI-y2GFjERepMZNdq1hVY?authuser=0&hl=th&rclk=1", "latitude": 15.2872294, "longitude": 104.8429947, "name": "สวนน้ำอุบลทองหล่อวิสต้า", "rating": 3.7, "review": "(191)", "trip_type": "สถานที่ท่องเที่ยว", "image": "https://lh5.googleusercontent.com/p/AF1QipMCz3sUwjWxrgtiyKHrnvwxwqtDOLhw-az76vyW=w199-h92-k-no"}}, {"model": "TourBuddy.trip", "pk": 157, "fields": {"location": "https://www.google.co.th/maps/place/%E0%B8%95%E0%B8%B1%E0%B8%99%E0%B9%84%E0%B8%97%E0%B8%A3%E0%B8%A2%E0%B8%B1%E0%B8%81%E0%B8%A9%E0%B9%8C+%E0%B8%AD%E0%B8%B8%E0%B8%9A%E0%B8%A5%E0%B8%A3%E0%B8%B2%E0%B8%8A%E0%B8%98%E0%B8%B2%E0%B8%99%E0%B8%B5/data=!4m7!3m6!1s0x3115d5f86d203c91:0x651a4e6ea7f429f2!8m2!3d15.290815!4d105.045778!16s%2Fg%2F11jcm5m346!19sChIJkTwgbfjVFTER8in0p25OGmU?authuser=0&hl=th&rclk=1", "latitude": 15.290815, "longitude": 105.045778, "name": "ตันไทรยักษ์ อุบลราชธานี", "rating": 4.0, "review": "(5)", "trip_type": "สถานที่ท่องเที่ยว", "image": "https://lh5.googleusercontent.com/p/AF1QipMj1VsVMDL1iYBWaJfMGK5h_pthV3_sSdhBXmnS=w163-h92-k-no"}}, {"model": "TourBuddy.trip", "pk": 158, "fields": {"location": "https://www.google.co.th/maps/place/MP+farm/data=!4m7!3m6!1s0x311671b8a21eb97d:0x96fa8d6497a97f8a!8m2!3d15.4649024!4d104.9175812!16s%2Fg%2F11m7xg9k6m!19sChIJfbkeorhxFjERin-pl2SN-pY?authuser=0&hl=th&rclk=1", "latitude": 15.4649024, "longitude": 104.9175812, "name": "MP farm", "rating": 5.0, "review": "(6)", "trip_type": "สถานที่ท่องเที่ยว", "image": "https://lh5.googleusercontent.com/p/AF1QipM8XjZTY-PLGyI9IukRl1lls5bAZURx9cINaUHt=w80-h106-k-no"}}, {"model": "TourBuddy.trip", "pk": 159, "fields": {"location": "https://www.google.co.th/maps/place/%E0%B8%81%E0%B8%B2%E0%B8%A3%E0%B8%97%E0%B9%88%E0%B8%AD%E0%B8%87%E0%B9%80%E0%B8%97%E0%B8%B5%E0%B9%88%E0%B8%A2%E0%B8%A7%E0%B9%81%E0%B8%AB%E0%B9%88%E0%B8%87%E0%B8%9B%E0%B8%A3%E0%B8%B0%E0%B9%80%E0%B8%97%E0%B8%A8%E0%B9%84%E0%B8%97%E0%B8%A2+%E0%B8%AA%E0%B8%B3%E0%B8%99%E0%B8%B1%E0%B8%81%E0%B8%87%E0%B8%B2%E0%B8%99%E0%B8%AD%E0%B8%B8%E0%B8%9A%E0%B8%A5%E0%B8%A3%E0%B8%B2%E0%B8%8A%E0%B8%98%E0%B8%B2%E0%B8%99%E0%B8%B5/data=!4m7!3m6!1s0x311686317f45f013:0x78e2c841a3c42b7a!8m2!3d15.2279423!4d104.8599968!16s%2Fg%2F11c6ly5d_3!19sChIJE_BFfzGGFjEReivEo0HI4ng?authuser=0&hl=th&rclk=1", "latitude": 15.2279423, "longitude": 104.8599968, "name": "การท่องเที่ยวแห่งประเทศไทย สำนักงานอุบลราชธานี", "rating": 4.3, "review": "(24)", "trip_type": "ศูนย์ข้อมูลนักท่องเที่ยว", "image": "https://lh5.googleusercontent.com/p/AF1QipNx2Zr8JGIl6EFy7beL79hDZpFIx14Mw9b8fgAH=w122-h92-k-no"}}, {"model": "TourBuddy.trip", "pk": 160, "fields": {"location": "https://www.google.co.th/maps/place/%E0%B8%9C%E0%B8%B2%E0%B9%82%E0%B8%AA%E0%B8%81/data=!4m7!3m6!1s0x3115bb782b9b4cb1:0x679a2e92a1da5a1f!8m2!3d15.4181331!4d105.5708919!16s%2Fg%2F11gmsd9pll!19sChIJsUybK3i7FTERH1raoZIummc?authuser=0&hl=th&rclk=1", "latitude": 15.4181331, "longitude": 105.5708919, "name": "ผาโสก", "rating": 4.8, "review": "(69)", "trip_type": "อุทยาน", "image": "https://lh5.googleusercontent.com/p/AF1QipNUGkymlZAdRMH25N2HEUbsWtrRGrV6scrLgXKl=w122-h92-k-no"}}, {"model": "TourBuddy.trip", "pk": 161, "fields": {"location": "https://www.google.co.th/maps/place/%E0%B8%97%E0%B8%B8%E0%B9%88%E0%B8%87%E0%B8%99%E0%B8%B2%E0%B8%A1%E0%B8%B7%E0%B8%AD%E0%B8%9B%E0%B8%A3%E0%B8%B2%E0%B8%9A%E2%80%8B+%E0%B8%88%E0%B8%AD%E0%B8%99%E0%B8%99%E0%B8%B5%E0%B9%88%E0%B8%9F%E0%B8%B2%E0%B8%A3%E0%B9%8C%E0%B8%A1%E0%B8%AA%E0%B9%80%E0%B8%95%E0%B8%A2%E0%B9%8C/data=!4m7!3m6!1s0x3115cd232aff7bed:0xa5cd8da4b4cefe91!8m2!3d15.2981569!4d105.2759424!16s%2Fg%2F11j94dz190!19sChIJ7Xv_KiPNFTERkf7OtKSNzaU?authuser=0&hl=th&rclk=1", "latitude": 15.2981569, "longitude": 105.2759424, "name": "ทุ่งนามือปราบ​ จอนนี่ฟาร์มสเตย์", "rating": 4.3, "review": "(788)", "trip_type": "สถานที่ท่องเที่ยว", "image": "https://lh5.googleusercontent.com/p/AF1QipOSnN0RubSxL2SKIhDuHdikh74OmnaX26sLCtco=w137-h92-k-no"}}, {"model": "TourBuddy.trip", "pk": 162, "fields": {"location": "https://www.google.co.th/maps/place/%E0%B8%AB%E0%B8%AD%E0%B9%84%E0%B8%95%E0%B8%A3%E0%B8%AB%E0%B8%A5%E0%B8%B1%E0%B8%81%E0%B8%84%E0%B8%B3%E0%B8%88%E0%B8%B1%E0%B8%99%E0%B8%97%E0%B8%A3%E0%B9%8C/data=!4m7!3m6!1s0x31166b92cd2051c7:0x40da32b29f135ca2!8m2!3d15.6505287!4d104.68773!16s%2Fg%2F11fqptznqx!19sChIJx1EgzZJrFjERolwTn7Iy2kA?authuser=0&hl=th&rclk=1", "latitude": 15.6505287, "longitude": 104.68773, "name": "หอไตรหลักคำจันทร์", "rating": 5.0, "review": "(4)", "trip_type": "สถานที่ท่องเที่ยว", "image": "https://lh5.googleusercontent.com/p/AF1QipMK8y04WwIZp0vq7RngHajKMjxDV9aEkedH-BB1=w122-h92-k-no"}}]